{"type": "Feature", "id": 28621865, "properties": {"woe:id": 28621865, "woe:parent_id": 28494588, "woe:name": "\u67f4\u7aef\u5225\u9928", "woe:placetype": 20, "woe:placetype_name": "POI", "woe:lang": "JPN", "iso:country": "JP", "meta:provider": ["geoplanet:7.3.1", "geoplanet:7.3.2", "geoplanet:7.4.0", "geoplanet:7.4.1", "geoplanet:7.5.1", "geoplanet:7.5.2", "geoplanet:7.6.0", "geoplanet:7.8.1", "geoplanet:7.9.0", "geoplanet:7.10.0", "geoplanet:8.0.0", "woeplanet:8.0.0"], "meta:indexed": "2020-08-20T20:47:37.815438", "meta:updated": "2020-08-22T02:46:12.109281", "woe:hierarchy": {"continent": 24865671, "country": 23424856, "town": 0, "planet": 1, "county": 0, "suburb": 0, "state": 2345864, "region": 0, "localadmin": 28494588}, "woe:timezone_id": 28350861, "woe:hash": "xn96gxcjyjce", "woe:centroid": [136.913254, 37.089489], "geom:latitude": 37.089489, "geom:longitude": 136.913254, "geom:hash": "xn96gxcjyjce", "woe:latitude": 37.089489, "geom:centroid": [136.913254, 37.089489], "woe:longitude": 136.913254, "woe:repo": "woeplanet-poi-jp"}, "geometry": {"coordinates": [136.913254, 37.089489], "type": "Point"}}