{"type": "Feature", "id": 28620742, "geometry": {"type": "Point", "coordinates": [139.626144, 35.451229]}, "properties": {"woe:id": 28620742, "woe:parent_id": 28415687, "woe:name": "\u30aa\u30ea\u30a8\u30f3\u30c8\u30db\u30c6\u30eb\u6a2a\u6ff1\u958b\u6d0b\u4ead", "woe:placetype": 20, "woe:placetype_name": "POI", "woe:lang": "JPN", "iso:country": "JP", "meta:provider": ["geoplanet:7.3.1", "geoplanet:7.3.2", "geoplanet:7.4.0", "geoplanet:7.4.1", "geoplanet:7.5.1", "geoplanet:7.5.2", "geoplanet:7.6.0", "geoplanet:7.8.1", "geoplanet:7.9.0", "geoplanet:7.10.0", "geoplanet:8.0.0", "woeplanet:8.0.0"], "meta:indexed": "2020-08-20T20:47:36.904389", "meta:updated": "2020-10-14T12:09:37.145424", "woe:hierarchy": {"continent": 24865671, "country": 23424856, "town": 0, "planet": 1, "county": 15015539, "suburb": 0, "state": 2345868, "region": 0, "localadmin": 28415687}, "woe:timezone_id": 28350861, "woe:hash": "xn739m8wkunf", "woe:centroid": [139.626144, 35.451229], "geom:latitude": 35.451229, "geom:longitude": 139.626144, "geom:hash": "xn739m8wkunf", "woe:latitude": 35.451229, "geom:centroid": [139.626144, 35.451229], "woe:longitude": 139.626144, "woe:repo": "woeplanet-poi-jp", "geom:area": 0.0, "woe:scale": 19}}