{"type": "Feature", "id": 28622916, "properties": {"woe:id": 28622916, "woe:parent_id": 28432076, "woe:name": "\u30db\u30c6\u30eb\u4ed9\u4eba\u95a3", "woe:placetype": 20, "woe:placetype_name": "POI", "woe:lang": "JPN", "iso:country": "JP", "meta:provider": ["geoplanet:7.3.1", "geoplanet:7.3.2", "geoplanet:7.4.0", "geoplanet:7.4.1", "geoplanet:7.5.1", "geoplanet:7.5.2", "geoplanet:7.6.0", "geoplanet:7.8.1", "geoplanet:7.9.0", "geoplanet:7.10.0", "geoplanet:8.0.0", "woeplanet:8.0.0"], "meta:indexed": "2020-08-20T20:47:38.613185", "woe:alias_JPN_V": ["\u307b\u3066\u308b\u305b\u3093\u306b\u3093\u304b\u304f"], "meta:updated": "2020-08-22T02:46:12.582289", "woe:alias_ENG_P": ["Hotel Senninkaku"], "woe:hierarchy": {"continent": 24865671, "country": 23424856, "town": 0, "planet": 1, "county": 0, "suburb": 0, "state": 2345875, "region": 0, "localadmin": 28432076}, "woe:timezone_id": 28350861, "woe:hash": "xn3zwee02sn3", "woe:centroid": [137.750732, 36.4939], "geom:latitude": 36.4939, "geom:longitude": 137.750732, "geom:hash": "xn3zwee02sn3", "woe:latitude": 36.4939, "geom:centroid": [137.750732, 36.4939], "woe:longitude": 137.750732, "woe:repo": "woeplanet-poi-jp"}, "geometry": {"coordinates": [137.750732, 36.4939], "type": "Point"}}