{"type": "Feature", "id": 28620420, "properties": {"woe:id": 28620420, "woe:parent_id": 28414057, "woe:name": "\u30db\u30c6\u30eb\u30a2\u30af\u30bb\u30b9\u30a4\u30f3\u65b0\u5bbf", "woe:placetype": 20, "woe:placetype_name": "POI", "woe:lang": "JPN", "iso:country": "JP", "meta:provider": ["geoplanet:7.3.1", "geoplanet:7.3.2", "geoplanet:7.4.0", "geoplanet:7.4.1", "geoplanet:7.5.1", "geoplanet:7.5.2", "geoplanet:7.6.0", "geoplanet:7.8.1", "geoplanet:7.9.0", "geoplanet:7.10.0", "geoplanet:8.0.0", "woeplanet:8.0.0"], "meta:indexed": "2020-08-20T20:47:36.647666", "woe:alias_JPN_V": ["\u65b0\u5bbf\u30b7\u30c6\u30a3\u30db\u30c6\u30eb\u9577\u6625\u9928", "\u307b\u3066\u308b\u3042\u304f\u305b\u3059\u3044\u3093\u3057\u3093\u3058\u3085\u304f"], "meta:updated": "2020-08-22T02:46:11.411914", "woe:alias_ENG_P": ["Hotel Access Inn Shinjuku"], "woe:hierarchy": {"continent": 24865671, "country": 23424856, "town": 0, "planet": 1, "county": 15015378, "suburb": 0, "state": 2345889, "region": 0, "localadmin": 28414057}, "woe:timezone_id": 28350861, "woe:hash": "xn7751728uss", "woe:centroid": [139.70665, 35.690571], "geom:latitude": 35.690571, "geom:longitude": 139.70665, "geom:hash": "xn7751728uss", "woe:latitude": 35.690571, "geom:centroid": [139.70665, 35.690571], "woe:longitude": 139.70665, "woe:repo": "woeplanet-poi-jp"}, "geometry": {"coordinates": [139.70665, 35.690571], "type": "Point"}}