{"type": "Feature", "id": 28618145, "properties": {"woe:id": 28618145, "woe:parent_id": 28395816, "woe:name": "\u7389\u5ddd\u6e29\u6cc9\u6e6f\u6cbb\u9928\u305d\u3088\u98a8", "woe:placetype": 20, "woe:placetype_name": "POI", "woe:lang": "JPN", "iso:country": "JP", "meta:provider": ["geoplanet:7.3.1", "geoplanet:7.3.2", "geoplanet:7.4.0", "geoplanet:7.4.1", "geoplanet:7.5.1", "geoplanet:7.5.2", "geoplanet:7.6.0", "geoplanet:7.8.1", "geoplanet:7.9.0", "geoplanet:7.10.0", "geoplanet:8.0.0", "woeplanet:8.0.0"], "meta:indexed": "2020-08-20T20:47:34.744069", "woe:alias_JPN_V": ["\u6e6f\u6cbb\u9928\u305d\u3088\u98a8", "\u305f\u307e\u304c\u308f\u304a\u3093\u305b\u3093\u3068\u3046\u3058\u304b\u3093\u305d\u3088\u304b\u305c"], "meta:updated": "2020-08-22T02:46:10.440134", "woe:alias_ENG_P": ["Tamagawa Onsen Tojikan Soyokaze"], "woe:hierarchy": {"continent": 24865671, "country": 23424856, "town": 0, "planet": 1, "county": 0, "suburb": 0, "state": 2345852, "region": 0, "localadmin": 28395816}, "woe:timezone_id": 28350861, "woe:hash": "xph564vhb270", "woe:centroid": [140.719772, 39.962212], "geom:latitude": 39.962212, "geom:longitude": 140.719772, "geom:hash": "xph564vhb270", "woe:latitude": 39.962212, "geom:centroid": [140.719772, 39.962212], "woe:longitude": 140.719772, "woe:repo": "woeplanet-poi-jp"}, "geometry": {"coordinates": [140.719772, 39.962212], "type": "Point"}}