{"type": "Feature", "id": 28617105, "properties": {"woe:id": 28617105, "woe:parent_id": 28384301, "woe:name": "\u5929\u4eba\u95a3", "woe:placetype": 20, "woe:placetype_name": "POI", "woe:lang": "JPN", "iso:country": "JP", "meta:provider": ["geoplanet:7.3.1", "geoplanet:7.3.2", "geoplanet:7.4.0", "geoplanet:7.4.1", "geoplanet:7.5.1", "geoplanet:7.5.2", "geoplanet:7.6.0", "geoplanet:7.8.1", "geoplanet:7.9.0", "geoplanet:7.10.0", "geoplanet:8.0.0", "woeplanet:8.0.0"], "meta:indexed": "2020-08-20T20:47:33.905432", "woe:alias_JPN_V": ["\u3066\u3093\u306b\u3093\u304b\u304f"], "meta:updated": "2020-08-22T02:46:10.078478", "woe:alias_ENG_P": ["Tenninkaku"], "woe:hierarchy": {"continent": 24865671, "country": 23424856, "town": 0, "planet": 1, "county": 24853906, "suburb": 0, "state": 7153351, "region": 0, "localadmin": 28384301}, "woe:timezone_id": 28350861, "woe:hash": "xpv81j19b2gs", "woe:centroid": [142.780396, 43.621521], "geom:latitude": 43.621521, "geom:longitude": 142.780396, "geom:hash": "xpv81j19b2gs", "woe:latitude": 43.621521, "geom:centroid": [142.780396, 43.621521], "woe:longitude": 142.780396, "woe:repo": "woeplanet-poi-jp"}, "geometry": {"coordinates": [142.780396, 43.621521], "type": "Point"}}