{"type": "Feature", "id": 28620058, "properties": {"woe:id": 28620058, "woe:parent_id": 1111714, "woe:name": "\u5bcc\u5d0e\u9928", "woe:placetype": 20, "woe:placetype_name": "POI", "woe:lang": "JPN", "iso:country": "JP", "meta:provider": ["geoplanet:7.3.1", "geoplanet:7.3.2", "geoplanet:7.4.0", "geoplanet:7.4.1", "geoplanet:7.5.1", "geoplanet:7.5.2", "geoplanet:7.6.0", "geoplanet:7.8.1", "geoplanet:7.9.0", "geoplanet:7.10.0", "geoplanet:8.0.0", "woeplanet:8.0.0"], "meta:indexed": "2020-08-20T20:47:36.387803", "woe:alias_JPN_V": ["\u3068\u307f\u3055\u304d\u304b\u3093"], "meta:updated": "2020-08-22T02:46:11.246049", "woe:alias_ENG_P": ["Tomisakikan"], "woe:hierarchy": {"continent": 24865671, "country": 23424856, "town": 0, "planet": 1, "county": 0, "suburb": 0, "state": 2345854, "region": 0, "localadmin": 1111714}, "woe:timezone_id": 28350861, "woe:hash": "xn5qtv4scjfh", "woe:centroid": [139.826477, 34.920891], "geom:latitude": 34.920891, "geom:longitude": 139.826477, "geom:hash": "xn5qtv4scjfh", "woe:latitude": 34.920891, "geom:centroid": [139.826477, 34.920891], "woe:longitude": 139.826477, "woe:repo": "woeplanet-poi-jp"}, "geometry": {"coordinates": [139.826477, 34.920891], "type": "Point"}}