{"type": "Feature", "id": 28620560, "geometry": {"type": "Point", "coordinates": [139.694504, 35.628632]}, "properties": {"woe:id": 28620560, "woe:parent_id": 28414261, "woe:name": "CLASKA", "woe:placetype": 20, "woe:placetype_name": "POI", "woe:lang": "JPN", "iso:country": "JP", "meta:provider": ["geoplanet:7.3.1", "geoplanet:7.3.2", "geoplanet:7.4.0", "geoplanet:7.4.1", "geoplanet:7.5.1", "geoplanet:7.5.2", "geoplanet:7.6.0", "geoplanet:7.8.1", "geoplanet:7.9.0", "geoplanet:7.10.0", "geoplanet:8.0.0", "woeplanet:8.0.0"], "meta:indexed": "2020-08-20T20:47:36.754331", "woe:alias_JPN_V": ["\u30db\u30c6\u30eb\u30cb\u30e5\u30fc\u30e1\u30b0\u30ed", "\u304f\u3089\u3059\u304b"], "meta:updated": "2020-10-14T12:09:53.494081", "woe:hierarchy": {"continent": 24865671, "country": 23424856, "town": 0, "planet": 1, "county": 15015504, "suburb": 0, "state": 2345889, "region": 0, "localadmin": 28414261}, "woe:timezone_id": 28350861, "woe:hash": "xn76dvfrvf7u", "woe:centroid": [139.694504, 35.628632], "geom:latitude": 35.628632, "geom:longitude": 139.694504, "geom:hash": "xn76dvfrvf7u", "woe:latitude": 35.628632, "geom:centroid": [139.694504, 35.628632], "woe:longitude": 139.694504, "woe:repo": "woeplanet-poi-jp", "geom:area": 0.0, "woe:scale": 19}}