{"type": "Feature", "id": 28617173, "geometry": {"type": "Point", "coordinates": [140.840073, 42.563889]}, "properties": {"woe:id": 28617173, "woe:parent_id": 28385306, "woe:name": "\u6e56\u7554\u306e\u5bbf\u6d1e\u723a\u304b\u308f\u306a\u307f", "woe:placetype": 20, "woe:placetype_name": "POI", "woe:lang": "JPN", "iso:country": "JP", "meta:provider": ["geoplanet:7.3.1", "geoplanet:7.3.2", "geoplanet:7.4.0", "geoplanet:7.4.1", "geoplanet:7.5.1", "geoplanet:7.5.2", "geoplanet:7.6.0", "geoplanet:7.8.1", "geoplanet:7.9.0", "geoplanet:7.10.0", "geoplanet:8.0.0", "woeplanet:8.0.0"], "meta:indexed": "2020-08-20T20:47:33.965834", "woe:alias_JPN_V": ["\u3053\u306f\u3093\u306e\u3084\u3069\u3068\u3046\u3084\u304b\u308f\u306a\u307f"], "meta:updated": "2020-10-14T12:09:39.800427", "woe:alias_ENG_P": ["Hotel Kawanami"], "woe:hierarchy": {"continent": 24865671, "country": 23424856, "town": 0, "planet": 1, "county": 24853922, "suburb": 0, "state": 7153351, "region": 0, "localadmin": 28385306}, "woe:timezone_id": 28350861, "woe:hash": "xps4hus8eefp", "woe:centroid": [140.840073, 42.563889], "geom:latitude": 42.563889, "geom:longitude": 140.840073, "geom:hash": "xps4hus8eefp", "woe:latitude": 42.563889, "geom:centroid": [140.840073, 42.563889], "woe:longitude": 140.840073, "woe:repo": "woeplanet-poi-jp", "geom:area": 0.0, "woe:scale": 19}}