{"type": "Feature", "id": 28621923, "geometry": {"type": "Point", "coordinates": [136.904266, 37.39323]}, "properties": {"woe:id": 28621923, "woe:parent_id": 28426793, "woe:name": "\u5ddd\u7aef\u65c5\u9928", "woe:placetype": 20, "woe:placetype_name": "POI", "woe:lang": "JPN", "iso:country": "JP", "meta:provider": ["geoplanet:7.3.1", "geoplanet:7.3.2", "geoplanet:7.4.0", "geoplanet:7.4.1", "geoplanet:7.5.1", "geoplanet:7.5.2", "geoplanet:7.6.0", "geoplanet:7.8.1", "geoplanet:7.9.0", "geoplanet:7.10.0", "geoplanet:8.0.0", "woeplanet:8.0.0"], "meta:indexed": "2020-08-20T20:47:37.860790", "meta:updated": "2020-10-14T12:09:36.891852", "woe:hierarchy": {"continent": 24865671, "country": 23424856, "town": 0, "planet": 1, "county": 0, "suburb": 0, "state": 2345864, "region": 0, "localadmin": 28426793}, "woe:timezone_id": 28350861, "woe:hash": "xn9ker4xke79", "woe:centroid": [136.904266, 37.39323], "geom:latitude": 37.39323, "geom:longitude": 136.904266, "geom:hash": "xn9ker4xke79", "woe:latitude": 37.39323, "geom:centroid": [136.904266, 37.39323], "woe:longitude": 136.904266, "woe:repo": "woeplanet-poi-jp", "geom:area": 0.0, "woe:scale": 19}}