{"type": "Feature", "id": 28621041, "geometry": {"type": "Point", "coordinates": [139.149719, 35.143391]}, "properties": {"woe:id": 28621041, "woe:parent_id": 28417503, "woe:name": "\u548c\u307f\u306e\u5bbf\u305f\u304b\u3046\u3089", "woe:placetype": 20, "woe:placetype_name": "POI", "woe:lang": "JPN", "iso:country": "JP", "meta:provider": ["geoplanet:7.3.1", "geoplanet:7.3.2", "geoplanet:7.4.0", "geoplanet:7.4.1", "geoplanet:7.5.1", "geoplanet:7.5.2", "geoplanet:7.6.0", "geoplanet:7.8.1", "geoplanet:7.9.0", "geoplanet:7.10.0", "geoplanet:8.0.0", "woeplanet:8.0.0"], "meta:indexed": "2020-08-20T20:47:37.145734", "woe:alias_JPN_V": ["\u5272\u70f9\u65c5\u9928\u3048\u3073\u306a", "\u306a\u3054\u307f\u306e\u3084\u3069\u305f\u304b\u3046\u3089"], "meta:updated": "2020-10-14T12:09:48.810989", "woe:alias_ENG_P": ["Nagominoyado Takaura"], "woe:hierarchy": {"continent": 24865671, "country": 23424856, "town": 0, "planet": 1, "county": 24857810, "suburb": 0, "state": 2345868, "region": 0, "localadmin": 28417503}, "woe:timezone_id": 28350861, "woe:hash": "xn4zymttp6yv", "woe:centroid": [139.149719, 35.143391], "geom:latitude": 35.143391, "geom:longitude": 139.149719, "geom:hash": "xn4zymttp6yv", "woe:latitude": 35.143391, "geom:centroid": [139.149719, 35.143391], "woe:longitude": 139.149719, "woe:repo": "woeplanet-poi-jp", "geom:area": 0.0, "woe:scale": 19}}