{"type": "Feature", "id": 28617848, "geometry": {"type": "Point", "coordinates": [141.625381, 38.86451]}, "properties": {"woe:id": 28617848, "woe:parent_id": 28391634, "woe:name": "\u4f11\u6687\u6751\u6c17\u4ed9\u6cbc\u5927\u5cf6", "woe:placetype": 20, "woe:placetype_name": "POI", "woe:lang": "JPN", "iso:country": "JP", "meta:provider": ["geoplanet:7.3.1", "geoplanet:7.3.2", "geoplanet:7.4.0", "geoplanet:7.4.1", "geoplanet:7.5.1", "geoplanet:7.5.2", "geoplanet:7.6.0", "geoplanet:7.8.1", "geoplanet:7.9.0", "geoplanet:7.10.0", "geoplanet:8.0.0", "woeplanet:8.0.0"], "meta:indexed": "2020-08-20T20:47:34.510832", "woe:alias_JPN_V": ["\u304d\u3085\u3046\u304b\u3080\u3089\u3051\u305b\u3093\u306c\u307e\u304a\u304a\u3057\u307e"], "meta:updated": "2020-10-14T12:09:40.285176", "woe:alias_ENG_P": ["Kyukamura Kesennuma Ooshima"], "woe:hierarchy": {"continent": 24865671, "country": 23424856, "town": 0, "planet": 1, "county": 0, "suburb": 0, "state": 2345873, "region": 0, "localadmin": 28391634}, "woe:timezone_id": 28350861, "woe:hash": "xnutng06ntf0", "woe:centroid": [141.625381, 38.86451], "geom:latitude": 38.86451, "geom:longitude": 141.625381, "geom:hash": "xnutng06ntf0", "woe:latitude": 38.86451, "geom:centroid": [141.625381, 38.86451], "woe:longitude": 141.625381, "woe:repo": "woeplanet-poi-jp", "geom:area": 0.0, "woe:scale": 19}}