{"type": "Feature", "id": 28619633, "properties": {"woe:id": 28619633, "woe:parent_id": 55807471, "woe:name": "\u6e56\u7554\u4ead", "woe:placetype": 20, "woe:placetype_name": "POI", "woe:lang": "JPN", "iso:country": "JP", "meta:provider": ["geoplanet:7.3.1", "geoplanet:7.3.2", "geoplanet:7.4.0", "geoplanet:7.4.1", "geoplanet:7.5.1", "geoplanet:7.5.2", "geoplanet:7.6.0", "geoplanet:7.8.1", "geoplanet:7.9.0", "geoplanet:7.10.0", "geoplanet:8.0.0", "woeplanet:8.0.0"], "meta:indexed": "2020-08-20T20:47:35.959347", "woe:alias_JPN_V": ["\u3053\u306f\u3093\u3066\u3044"], "meta:updated": "2020-08-22T02:46:11.051282", "woe:alias_ENG_P": ["Kohantei"], "woe:hierarchy": {"continent": 24865671, "country": 23424856, "town": 0, "planet": 1, "county": 0, "suburb": 0, "state": 2345860, "region": 0, "localadmin": 55807471}, "woe:timezone_id": 28350861, "woe:hash": "xn6xrzhz8us1", "woe:centroid": [138.862762, 36.470428], "geom:latitude": 36.470428, "geom:longitude": 138.862762, "geom:hash": "xn6xrzhz8us1", "woe:latitude": 36.470428, "geom:centroid": [138.862762, 36.470428], "woe:longitude": 138.862762, "woe:repo": "woeplanet-poi-jp"}, "geometry": {"coordinates": [138.862762, 36.470428], "type": "Point"}}