{"type": "Feature", "id": 28622064, "geometry": {"type": "Point", "coordinates": [136.720535, 37.150421]}, "properties": {"woe:id": 28622064, "woe:parent_id": 28427941, "woe:name": "\u5bcc\u6765\u30b5\u30a4\u30af\u30ea\u30f3\u30b0\u30bf\u30fc\u30df\u30ca\u30eb", "woe:placetype": 20, "woe:placetype_name": "POI", "woe:lang": "JPN", "iso:country": "JP", "meta:provider": ["geoplanet:7.3.1", "geoplanet:7.3.2", "geoplanet:7.4.0", "geoplanet:7.4.1", "geoplanet:7.5.1", "geoplanet:7.5.2", "geoplanet:7.6.0", "geoplanet:7.8.1", "geoplanet:7.9.0", "geoplanet:7.10.0", "geoplanet:8.0.0", "woeplanet:8.0.0"], "meta:indexed": "2020-08-20T20:47:37.961551", "meta:updated": "2020-10-14T12:09:54.665005", "woe:hierarchy": {"continent": 24865671, "country": 23424856, "town": 0, "planet": 1, "county": 24854126, "suburb": 0, "state": 2345864, "region": 0, "localadmin": 28427941}, "woe:timezone_id": 28350861, "woe:hash": "xn95r5hbgk7v", "woe:centroid": [136.720535, 37.150421], "geom:latitude": 37.150421, "geom:longitude": 136.720535, "geom:hash": "xn95r5hbgk7v", "woe:latitude": 37.150421, "geom:centroid": [136.720535, 37.150421], "woe:longitude": 136.720535, "woe:repo": "woeplanet-poi-jp", "geom:area": 0.0, "woe:scale": 19}}