{"type": "Feature", "id": 28621107, "properties": {"woe:id": 28621107, "woe:parent_id": 55807729, "woe:name": "\u30cb\u30e5\u30fc\u8d8a\u8def", "woe:placetype": 20, "woe:placetype_name": "POI", "woe:lang": "JPN", "iso:country": "JP", "meta:provider": ["geoplanet:7.3.1", "geoplanet:7.3.2", "geoplanet:7.4.0", "geoplanet:7.4.1", "geoplanet:7.5.1", "geoplanet:7.5.2", "geoplanet:7.6.0", "geoplanet:7.8.1", "geoplanet:7.9.0", "geoplanet:7.10.0", "geoplanet:8.0.0", "woeplanet:8.0.0"], "meta:indexed": "2020-08-20T20:47:37.199449", "meta:updated": "2020-08-22T02:46:11.762370", "woe:hierarchy": {"continent": 24865671, "country": 23424856, "town": 0, "planet": 1, "county": 55805803, "suburb": 0, "state": 2345878, "region": 0, "localadmin": 55807729}, "woe:timezone_id": 28350861, "woe:hash": "xndzsqr8nrhk", "woe:centroid": [139.064529, 37.91523], "geom:latitude": 37.91523, "geom:longitude": 139.064529, "geom:hash": "xndzsqr8nrhk", "woe:latitude": 37.91523, "geom:centroid": [139.064529, 37.91523], "woe:longitude": 139.064529, "woe:repo": "woeplanet-poi-jp"}, "geometry": {"coordinates": [139.064529, 37.91523], "type": "Point"}}