{"type": "Feature", "id": 28619034, "geometry": {"type": "Point", "coordinates": [140.538742, 36.384121]}, "properties": {"woe:id": 28619034, "woe:parent_id": 28403012, "woe:name": "\u30db\u30c6\u30eb\u30af\u30ea\u30b9\u30bf\u30eb\u30d1\u30ec\u30b9\u9577\u5bff\u8358", "woe:placetype": 20, "woe:placetype_name": "POI", "woe:lang": "JPN", "iso:country": "JP", "meta:provider": ["geoplanet:7.3.1", "geoplanet:7.3.2", "geoplanet:7.4.0", "geoplanet:7.4.1", "geoplanet:7.5.1", "geoplanet:7.5.2", "geoplanet:7.6.0", "geoplanet:7.8.1", "geoplanet:7.9.0", "geoplanet:7.10.0", "geoplanet:8.0.0", "woeplanet:8.0.0"], "meta:indexed": "2020-08-20T20:47:35.471735", "woe:alias_JPN_V": ["\u307b\u3066\u308b\u304f\u308a\u3059\u305f\u308b\u3071\u308c\u3059\u3061\u3087\u3046\u3058\u3085\u305d\u3046"], "meta:updated": "2020-10-14T12:09:45.350644", "woe:alias_ENG_P": ["Hotel Crystal Palace Chozuso"], "woe:hierarchy": {"continent": 24865671, "country": 23424856, "town": 0, "planet": 1, "county": 0, "suburb": 0, "state": 2345863, "region": 0, "localadmin": 28403012}, "woe:timezone_id": 28350861, "woe:hash": "xn7yyp90y59r", "woe:centroid": [140.538742, 36.384121], "geom:latitude": 36.384121, "geom:longitude": 140.538742, "geom:hash": "xn7yyp90y59r", "woe:latitude": 36.384121, "geom:centroid": [140.538742, 36.384121], "woe:longitude": 140.538742, "woe:repo": "woeplanet-poi-jp", "geom:area": 0.0, "woe:scale": 19}}