{"type": "Feature", "id": 28621634, "properties": {"woe:id": 28621634, "woe:parent_id": 28423963, "woe:name": "\u30db\u30c6\u30eb\uff2b\uff06\uff27\u9ad8\u5ca1", "woe:placetype": 20, "woe:placetype_name": "POI", "woe:lang": "JPN", "iso:country": "JP", "meta:provider": ["geoplanet:7.3.1", "geoplanet:7.3.2", "geoplanet:7.4.0", "geoplanet:7.4.1", "geoplanet:7.5.1", "geoplanet:7.5.2", "geoplanet:7.6.0", "geoplanet:7.8.1", "geoplanet:7.9.0", "geoplanet:7.10.0", "geoplanet:8.0.0", "woeplanet:8.0.0"], "meta:indexed": "2020-08-20T20:47:37.641690", "meta:updated": "2020-08-22T02:46:12.006235", "woe:hierarchy": {"continent": 24865671, "country": 23424856, "town": 0, "planet": 1, "county": 0, "suburb": 0, "state": 2345891, "region": 0, "localadmin": 28423963}, "woe:timezone_id": 28350861, "woe:hash": "xn93jb698m7s", "woe:centroid": [137.013947, 36.739941], "geom:latitude": 36.739941, "geom:longitude": 137.013947, "geom:hash": "xn93jb698m7s", "woe:latitude": 36.739941, "geom:centroid": [137.013947, 36.739941], "woe:longitude": 137.013947, "woe:repo": "woeplanet-poi-jp"}, "geometry": {"coordinates": [137.013947, 36.739941], "type": "Point"}}