{"type": "Feature", "id": 28619584, "geometry": {"type": "Point", "coordinates": [138.924393, 36.498798]}, "properties": {"woe:id": 28619584, "woe:parent_id": 28407036, "woe:name": "\u4f0a\u9999\u4fdd\u89b3\u5149\u30db\u30c6\u30eb", "woe:placetype": 20, "woe:placetype_name": "POI", "woe:lang": "JPN", "iso:country": "JP", "meta:provider": ["geoplanet:7.3.1", "geoplanet:7.3.2", "geoplanet:7.4.0", "geoplanet:7.4.1", "geoplanet:7.5.1", "geoplanet:7.5.2", "geoplanet:7.6.0", "geoplanet:7.8.1", "geoplanet:7.9.0", "geoplanet:7.10.0", "geoplanet:8.0.0", "woeplanet:8.0.0"], "meta:indexed": "2020-08-20T20:47:35.921612", "meta:updated": "2020-10-14T12:09:45.172591", "woe:hierarchy": {"continent": 24865671, "country": 23424856, "town": 0, "planet": 1, "county": 0, "suburb": 0, "state": 2345860, "region": 0, "localadmin": 28407036}, "woe:timezone_id": 28350861, "woe:hash": "xn6z9k3suvpd", "woe:centroid": [138.924393, 36.498798], "geom:latitude": 36.498798, "geom:longitude": 138.924393, "geom:hash": "xn6z9k3suvpd", "woe:latitude": 36.498798, "geom:centroid": [138.924393, 36.498798], "woe:longitude": 138.924393, "woe:repo": "woeplanet-poi-jp", "geom:area": 0.0, "woe:scale": 19}}