{"type": "Feature", "id": 28620547, "geometry": {"type": "Point", "coordinates": [139.737167, 35.621342]}, "properties": {"woe:id": 28620547, "woe:parent_id": 28414229, "woe:name": "\u5fa1\u6bbf\u5c71\u30ac\u30fc\u30c7\u30f3\u30db\u30c6\u30eb\u30e9\u30d5\u30a9\u30fc\u30ec\u6771\u4eac", "woe:placetype": 20, "woe:placetype_name": "POI", "woe:lang": "JPN", "iso:country": "JP", "meta:provider": ["geoplanet:7.3.1", "geoplanet:7.3.2", "geoplanet:7.4.0", "geoplanet:7.4.1", "geoplanet:7.5.1", "geoplanet:7.5.2", "geoplanet:7.6.0", "geoplanet:7.8.1", "geoplanet:7.9.0", "geoplanet:7.10.0", "geoplanet:8.0.0", "woeplanet:8.0.0"], "meta:indexed": "2020-08-20T20:47:36.744800", "woe:alias_JPN_V": ["\u5fa1\u6bbf\u5c71\u30d2\u30eb\u30ba\u30db\u30c6\u30eb\u30e9\u30d5\u30a9\u30fc\u30ec\u6771\u4eac", "\u3054\u3066\u3093\u3084\u307e\u304c\u30fc\u3067\u3093\u307b\u3066\u308b\u3089\u3075\u3049\u30fc\u308c\u3068\u3046\u304d\u3087\u3046"], "meta:updated": "2020-10-14T12:09:53.497398", "woe:alias_ENG_P": ["Gotenyama Garden Hotel Laforet Tokyo"], "woe:hierarchy": {"continent": 24865671, "country": 23424856, "town": 0, "planet": 1, "county": 15015507, "suburb": 0, "state": 2345889, "region": 0, "localadmin": 28414229}, "woe:timezone_id": 28350861, "woe:hash": "xn76eu9mrgrt", "woe:centroid": [139.737167, 35.621342], "geom:latitude": 35.621342, "geom:longitude": 139.737167, "geom:hash": "xn76eu9mrgrt", "woe:latitude": 35.621342, "geom:centroid": [139.737167, 35.621342], "woe:longitude": 139.737167, "woe:repo": "woeplanet-poi-jp", "geom:area": 0.0, "woe:scale": 19}}