{"type": "Feature", "id": 28621129, "geometry": {"type": "Point", "coordinates": [139.040253, 37.915489]}, "properties": {"woe:id": 28621129, "woe:parent_id": 55807748, "woe:name": "\u8d8a\u4e43\u5bd2\u6885\u3068\u7518\u3048\u3073\u306e\u5bbf\u306b\u3057\u3084\u307e", "woe:placetype": 20, "woe:placetype_name": "POI", "woe:lang": "JPN", "iso:country": "JP", "meta:provider": ["geoplanet:7.3.1", "geoplanet:7.3.2", "geoplanet:7.4.0", "geoplanet:7.4.1", "geoplanet:7.5.1", "geoplanet:7.5.2", "geoplanet:7.6.0", "geoplanet:7.8.1", "geoplanet:7.9.0", "geoplanet:7.10.0", "geoplanet:8.0.0", "woeplanet:8.0.0"], "meta:indexed": "2020-08-20T20:47:37.218622", "woe:alias_JPN_V": ["\u3053\u3057\u306e\u304b\u3093\u3070\u3044\u3068\u3042\u307e\u3048\u3073\u306e\u3084\u3069\u306b\u3057\u3084\u307e"], "meta:updated": "2020-10-14T12:09:41.641450", "woe:alias_ENG_P": ["Koshinokanbai To Amaebi No Yado Nishiyama"], "woe:hierarchy": {"continent": 24865671, "country": 23424856, "town": 0, "planet": 1, "county": 55805803, "suburb": 0, "state": 2345878, "region": 0, "localadmin": 55807748}, "woe:timezone_id": 28350861, "woe:hash": "xndzeyq18xqv", "woe:centroid": [139.040253, 37.915489], "geom:latitude": 37.915489, "geom:longitude": 139.040253, "geom:hash": "xndzeyq18xqv", "woe:latitude": 37.915489, "geom:centroid": [139.040253, 37.915489], "woe:longitude": 139.040253, "woe:repo": "woeplanet-poi-jp", "geom:area": 0.0, "woe:scale": 19}}