{"type": "Feature", "id": 28619702, "geometry": {"type": "Point", "coordinates": [138.510239, 36.639751]}, "properties": {"woe:id": 28619702, "woe:parent_id": 28407401, "woe:name": "\u4e07\u5ea7\u4ead\u5225\u9928", "woe:placetype": 20, "woe:placetype_name": "POI", "woe:lang": "JPN", "iso:country": "JP", "meta:provider": ["geoplanet:7.3.1", "geoplanet:7.3.2", "geoplanet:7.4.0", "geoplanet:7.4.1", "geoplanet:7.5.1", "geoplanet:7.5.2", "geoplanet:7.6.0", "geoplanet:7.8.1", "geoplanet:7.9.0", "geoplanet:7.10.0", "geoplanet:8.0.0", "woeplanet:8.0.0"], "meta:indexed": "2020-08-20T20:47:36.015553", "woe:alias_JPN_V": ["\u307e\u3093\u3056\u3066\u3044\u3079\u3063\u304b\u3093"], "meta:updated": "2020-10-14T12:09:53.239347", "woe:alias_ENG_P": ["Manzatei Bekkan"], "woe:hierarchy": {"continent": 24865671, "country": 23424856, "town": 0, "planet": 1, "county": 24857146, "suburb": 0, "state": 2345860, "region": 0, "localadmin": 28407401}, "woe:timezone_id": 28350861, "woe:hash": "xnd2ryh442xu", "woe:centroid": [138.510239, 36.639751], "geom:latitude": 36.639751, "geom:longitude": 138.510239, "geom:hash": "xnd2ryh442xu", "woe:latitude": 36.639751, "geom:centroid": [138.510239, 36.639751], "woe:longitude": 138.510239, "woe:repo": "woeplanet-poi-jp", "geom:area": 0.0, "woe:scale": 19}}