{"type": "Feature", "id": 28619257, "properties": {"woe:id": 28619257, "woe:parent_id": 1108063, "woe:name": "\u9b3c\u6012\u5ddd\u89b3\u5149\u30db\u30c6\u30eb\u6771\u9928", "woe:placetype": 20, "woe:placetype_name": "POI", "woe:lang": "JPN", "iso:country": "JP", "meta:provider": ["geoplanet:7.3.1", "geoplanet:7.3.2", "geoplanet:7.4.0", "geoplanet:7.4.1", "geoplanet:7.5.1", "geoplanet:7.5.2", "geoplanet:7.6.0", "geoplanet:7.8.1", "geoplanet:7.9.0", "geoplanet:7.10.0", "geoplanet:8.0.0", "woeplanet:8.0.0"], "meta:indexed": "2020-08-20T20:47:35.654521", "meta:updated": "2020-08-22T02:46:10.869923", "woe:hierarchy": {"continent": 24865671, "country": 23424856, "town": 0, "planet": 1, "county": 0, "suburb": 0, "state": 2345887, "region": 0, "localadmin": 1108063}, "woe:timezone_id": 28350861, "woe:hash": "xne3e3m445s7", "woe:centroid": [139.720093, 36.833401], "geom:latitude": 36.833401, "geom:longitude": 139.720093, "geom:hash": "xne3e3m445s7", "woe:latitude": 36.833401, "geom:centroid": [139.720093, 36.833401], "woe:longitude": 139.720093, "woe:repo": "woeplanet-poi-jp"}, "geometry": {"coordinates": [139.720093, 36.833401], "type": "Point"}}