{"type": "Feature", "id": 28616670, "geometry": {"type": "Point", "coordinates": [141.040604, 43.14196]}, "properties": {"woe:id": 28616670, "woe:parent_id": 28380357, "woe:name": "\u304b\u3093\u307d\u306e\u5bbf\u5c0f\u6a3d", "woe:placetype": 20, "woe:placetype_name": "POI", "woe:lang": "JPN", "iso:country": "JP", "meta:provider": ["geoplanet:7.3.1", "geoplanet:7.3.2", "geoplanet:7.4.0", "geoplanet:7.4.1", "geoplanet:7.5.1", "geoplanet:7.5.2", "geoplanet:7.6.0", "geoplanet:7.8.1", "geoplanet:7.9.0", "geoplanet:7.10.0", "geoplanet:8.0.0", "woeplanet:8.0.0"], "meta:indexed": "2020-08-20T20:47:33.510248", "woe:alias_JPN_V": ["\u304b\u3093\u307d\u306e\u3084\u3069\u304a\u305f\u308b"], "meta:updated": "2020-10-14T12:09:47.786442", "woe:alias_ENG_P": ["Kampo No Yado Otaru"], "woe:hierarchy": {"continent": 24865671, "country": 23424856, "town": 0, "planet": 1, "county": 0, "suburb": 0, "state": 7153351, "region": 0, "localadmin": 28380357}, "woe:timezone_id": 28350861, "woe:hash": "xpsm3my8hk0z", "woe:centroid": [141.040604, 43.14196], "geom:latitude": 43.14196, "geom:longitude": 141.040604, "geom:hash": "xpsm3my8hk0z", "woe:latitude": 43.14196, "geom:centroid": [141.040604, 43.14196], "woe:longitude": 141.040604, "woe:repo": "woeplanet-poi-jp", "geom:area": 0.0, "woe:scale": 19}}