{"type": "Feature", "id": 28618701, "properties": {"woe:id": 28618701, "woe:parent_id": 28398718, "woe:name": "\u820c\u9f13\u306e\u5bbf\u6d5c\u3068\u304f", "woe:placetype": 20, "woe:placetype_name": "POI", "woe:lang": "JPN", "iso:country": "JP", "meta:provider": ["geoplanet:7.3.1", "geoplanet:7.3.2", "geoplanet:7.4.0", "geoplanet:7.4.1", "geoplanet:7.5.1", "geoplanet:7.5.2", "geoplanet:7.6.0", "geoplanet:7.8.1", "geoplanet:7.9.0", "geoplanet:7.10.0", "geoplanet:8.0.0", "woeplanet:8.0.0"], "meta:indexed": "2020-08-20T20:47:35.187943", "woe:alias_JPN_V": ["\u6d77\u9bae\u95a3\u6d5c\u5fb3\u65c5\u9928", "\u3057\u305f\u3064\u3065\u307f\u306e\u3084\u3069\u306f\u307e\u3068\u304f"], "meta:updated": "2020-08-22T02:46:10.641465", "woe:alias_ENG_P": ["Shitatsuzumi No Yado Hamatoku"], "woe:hierarchy": {"continent": 24865671, "country": 23424856, "town": 0, "planet": 1, "county": 0, "suburb": 0, "state": 2345858, "region": 0, "localadmin": 28398718}, "woe:timezone_id": 28350861, "woe:hash": "xns4kqg4s62y", "woe:centroid": [140.816071, 36.995529], "geom:latitude": 36.995529, "geom:longitude": 140.816071, "geom:hash": "xns4kqg4s62y", "woe:latitude": 36.995529, "geom:centroid": [140.816071, 36.995529], "woe:longitude": 140.816071, "woe:repo": "woeplanet-poi-jp"}, "geometry": {"coordinates": [140.816071, 36.995529], "type": "Point"}}