{"type": "Feature", "id": 28616791, "geometry": {"type": "Point", "coordinates": [143.203201, 42.922009]}, "properties": {"woe:id": 28616791, "woe:parent_id": 28381002, "woe:name": "\u30db\u30c6\u30eb\u30d1\u30b3\u5e2f\u5e83\uff13", "woe:placetype": 20, "woe:placetype_name": "POI", "woe:lang": "JPN", "iso:country": "JP", "meta:provider": ["geoplanet:7.3.1", "geoplanet:7.3.2", "geoplanet:7.4.0", "geoplanet:7.4.1", "geoplanet:7.5.1", "geoplanet:7.5.2", "geoplanet:7.6.0", "geoplanet:7.8.1", "geoplanet:7.9.0", "geoplanet:7.10.0", "geoplanet:8.0.0", "woeplanet:8.0.0"], "meta:indexed": "2020-08-20T20:47:33.614647", "woe:alias_JPN_V": ["\u307b\u3066\u308b\u3071\u3053\u304a\u3073\u3072\u308d\uff13"], "meta:updated": "2020-10-14T12:09:37.666576", "woe:alias_ENG_P": ["Hotel Paco Obihiro3"], "woe:hierarchy": {"continent": 24865671, "country": 23424856, "town": 0, "planet": 1, "county": 0, "suburb": 0, "state": 7153351, "region": 0, "localadmin": 28381002}, "woe:timezone_id": 28350861, "woe:hash": "xptu4ttqu6qh", "woe:centroid": [143.203201, 42.922009], "geom:latitude": 42.922009, "geom:longitude": 143.203201, "geom:hash": "xptu4ttqu6qh", "woe:latitude": 42.922009, "geom:centroid": [143.203201, 42.922009], "woe:longitude": 143.203201, "woe:repo": "woeplanet-poi-jp", "geom:area": 0.0, "woe:scale": 19}}