{"type": "Feature", "id": 28622043, "properties": {"woe:id": 28622043, "woe:parent_id": 28427516, "woe:name": "\u677e\u4efb\u30b7\u30c6\u30a3\u30db\u30c6\u30eb\u767d\u5c71", "woe:placetype": 20, "woe:placetype_name": "POI", "woe:lang": "JPN", "iso:country": "JP", "meta:provider": ["geoplanet:7.3.1", "geoplanet:7.3.2", "geoplanet:7.4.0", "geoplanet:7.4.1", "geoplanet:7.5.1", "geoplanet:7.5.2", "geoplanet:7.6.0", "geoplanet:7.8.1", "geoplanet:7.9.0", "geoplanet:7.10.0", "geoplanet:8.0.0", "woeplanet:8.0.0"], "meta:indexed": "2020-08-20T20:47:37.947826", "meta:updated": "2020-08-22T02:46:12.186513", "woe:hierarchy": {"continent": 24865671, "country": 23424856, "town": 0, "planet": 1, "county": 0, "suburb": 0, "state": 2345864, "region": 0, "localadmin": 28427516}, "woe:timezone_id": 28350861, "woe:hash": "xn3pgcyxr3r0", "woe:centroid": [136.580292, 36.529419], "geom:latitude": 36.529419, "geom:longitude": 136.580292, "geom:hash": "xn3pgcyxr3r0", "woe:latitude": 36.529419, "geom:centroid": [136.580292, 36.529419], "woe:longitude": 136.580292, "woe:repo": "woeplanet-poi-jp"}, "geometry": {"coordinates": [136.580292, 36.529419], "type": "Point"}}