{"type": "Feature", "id": 28616781, "geometry": {"type": "Point", "coordinates": [143.203308, 42.92701]}, "properties": {"woe:id": 28616781, "woe:parent_id": 28381002, "woe:name": "\u30a2\u30eb\u30d5\u30a1\uff15\u30db\u30c6\u30eb", "woe:placetype": 20, "woe:placetype_name": "POI", "woe:lang": "JPN", "iso:country": "JP", "meta:provider": ["geoplanet:7.3.1", "geoplanet:7.3.2", "geoplanet:7.4.0", "geoplanet:7.4.1", "geoplanet:7.5.1", "geoplanet:7.5.2", "geoplanet:7.6.0", "geoplanet:7.8.1", "geoplanet:7.9.0", "geoplanet:7.10.0", "geoplanet:8.0.0", "woeplanet:8.0.0"], "meta:indexed": "2020-08-20T20:47:33.605963", "meta:updated": "2020-10-14T12:09:37.678621", "woe:hierarchy": {"continent": 24865671, "country": 23424856, "town": 0, "planet": 1, "county": 0, "suburb": 0, "state": 7153351, "region": 0, "localadmin": 28381002}, "woe:timezone_id": 28350861, "woe:hash": "xptu4wt7yytu", "woe:centroid": [143.203308, 42.92701], "geom:latitude": 42.92701, "geom:longitude": 143.203308, "geom:hash": "xptu4wt7yytu", "woe:latitude": 42.92701, "geom:centroid": [143.203308, 42.92701], "woe:longitude": 143.203308, "woe:repo": "woeplanet-poi-jp", "geom:area": 0.0, "woe:scale": 19}}