{"type": "Feature", "id": 28617342, "geometry": {"type": "Point", "coordinates": [140.483765, 40.597469]}, "properties": {"woe:id": 28617342, "woe:parent_id": 28387332, "woe:name": "\u30db\u30c6\u30eb\u65b0\u5bbf", "woe:placetype": 20, "woe:placetype_name": "POI", "woe:lang": "JPN", "iso:country": "JP", "meta:provider": ["geoplanet:7.3.1", "geoplanet:7.3.2", "geoplanet:7.4.0", "geoplanet:7.4.1", "geoplanet:7.5.1", "geoplanet:7.5.2", "geoplanet:7.6.0", "geoplanet:7.8.1", "geoplanet:7.9.0", "geoplanet:7.10.0", "geoplanet:8.0.0", "woeplanet:8.0.0"], "meta:indexed": "2020-08-20T20:47:34.121645", "woe:alias_JPN_V": ["\u307b\u3066\u308b\u3057\u3093\u3058\u3085\u304f"], "meta:updated": "2020-10-14T12:09:49.386593", "woe:alias_ENG_P": ["Hotel Shinjuku"], "woe:hierarchy": {"continent": 24865671, "country": 23424856, "town": 0, "planet": 1, "county": 0, "suburb": 0, "state": 2345853, "region": 0, "localadmin": 28387332}, "woe:timezone_id": 28350861, "woe:hash": "xp5yuy91kuxx", "woe:centroid": [140.483765, 40.597469], "geom:latitude": 40.597469, "geom:longitude": 140.483765, "geom:hash": "xp5yuy91kuxx", "woe:latitude": 40.597469, "geom:centroid": [140.483765, 40.597469], "woe:longitude": 140.483765, "woe:repo": "woeplanet-poi-jp", "geom:area": 0.0, "woe:scale": 19}}