{"type": "Feature", "id": 28619140, "geometry": {"type": "Point", "coordinates": [139.883026, 36.542858]}, "properties": {"woe:id": 28619140, "woe:parent_id": 28404558, "woe:name": "\u5b87\u90fd\u5bae\u30b0\u30e9\u30f3\u30c9\u30db\u30c6\u30eb", "woe:placetype": 20, "woe:placetype_name": "POI", "woe:lang": "JPN", "iso:country": "JP", "meta:provider": ["geoplanet:7.3.1", "geoplanet:7.3.2", "geoplanet:7.4.0", "geoplanet:7.4.1", "geoplanet:7.5.1", "geoplanet:7.5.2", "geoplanet:7.6.0", "geoplanet:7.8.1", "geoplanet:7.9.0", "geoplanet:7.10.0", "geoplanet:8.0.0", "woeplanet:8.0.0"], "meta:indexed": "2020-08-20T20:47:35.562063", "woe:alias_JPN_V": ["\u3046\u3064\u306e\u307f\u3084\u3050\u3089\u3093\u3069\u307b\u3066\u308b"], "meta:updated": "2020-10-14T12:09:49.338524", "woe:alias_ENG_P": ["Utsunomiya Grand Hotel"], "woe:hierarchy": {"continent": 24865671, "country": 23424856, "town": 0, "planet": 1, "county": 0, "suburb": 0, "state": 2345887, "region": 0, "localadmin": 28404558}, "woe:timezone_id": 28350861, "woe:hash": "xn7rzh7twf2n", "woe:centroid": [139.883026, 36.542858], "geom:latitude": 36.542858, "geom:longitude": 139.883026, "geom:hash": "xn7rzh7twf2n", "woe:latitude": 36.542858, "geom:centroid": [139.883026, 36.542858], "woe:longitude": 139.883026, "woe:repo": "woeplanet-poi-jp", "geom:area": 0.0, "woe:scale": 19}}