{"type": "Feature", "id": 28618591, "geometry": {"type": "Point", "coordinates": [139.925125, 37.499851]}, "properties": {"woe:id": 28618591, "woe:parent_id": 28398261, "woe:name": "\u30db\u30c6\u30eb\u7389\u5ddd", "woe:placetype": 20, "woe:placetype_name": "POI", "woe:lang": "JPN", "iso:country": "JP", "meta:provider": ["geoplanet:7.3.1", "geoplanet:7.3.2", "geoplanet:7.4.0", "geoplanet:7.4.1", "geoplanet:7.5.1", "geoplanet:7.5.2", "geoplanet:7.6.0", "geoplanet:7.8.1", "geoplanet:7.9.0", "geoplanet:7.10.0", "geoplanet:8.0.0", "woeplanet:8.0.0"], "meta:indexed": "2020-08-20T20:47:35.098990", "woe:alias_JPN_V": ["\u307b\u3066\u308b\u305f\u307e\u304c\u308f"], "meta:updated": "2020-10-14T12:09:37.459949", "woe:alias_ENG_P": ["Hotel Tamagawa"], "woe:hierarchy": {"continent": 24865671, "country": 23424856, "town": 0, "planet": 1, "county": 0, "suburb": 0, "state": 2345858, "region": 0, "localadmin": 28398261}, "woe:timezone_id": 28350861, "woe:hash": "xnet24dk7wzk", "woe:centroid": [139.925125, 37.499851], "geom:latitude": 37.499851, "geom:longitude": 139.925125, "geom:hash": "xnet24dk7wzk", "woe:latitude": 37.499851, "geom:centroid": [139.925125, 37.499851], "woe:longitude": 139.925125, "woe:repo": "woeplanet-poi-jp", "geom:area": 0.0, "woe:scale": 19}}