{"type": "Feature", "id": 28620423, "properties": {"woe:id": 28620423, "woe:parent_id": 26198499, "woe:name": "\u65b0\u5bbf\u30d1\u30ec\u30b9\u30db\u30c6\u30eb", "woe:placetype": 20, "woe:placetype_name": "POI", "woe:lang": "JPN", "iso:country": "JP", "meta:provider": ["geoplanet:7.3.1", "geoplanet:7.3.2", "geoplanet:7.4.0", "geoplanet:7.4.1", "geoplanet:7.5.1", "geoplanet:7.5.2", "geoplanet:7.6.0", "geoplanet:7.8.1", "geoplanet:7.9.0", "geoplanet:7.10.0", "geoplanet:8.0.0", "woeplanet:8.0.0"], "meta:indexed": "2020-08-20T20:47:36.649589", "meta:updated": "2020-08-22T02:46:11.413379", "woe:hierarchy": {"continent": 24865671, "country": 23424856, "town": 0, "planet": 1, "county": 15015378, "suburb": 0, "state": 2345889, "region": 0, "localadmin": 26198499}, "woe:timezone_id": 28350861, "woe:hash": "xn77544f34xx", "woe:centroid": [139.705978, 35.694981], "geom:latitude": 35.694981, "geom:longitude": 139.705978, "geom:hash": "xn77544f34xx", "woe:latitude": 35.694981, "geom:centroid": [139.705978, 35.694981], "woe:longitude": 139.705978, "woe:repo": "woeplanet-poi-jp"}, "geometry": {"coordinates": [139.705978, 35.694981], "type": "Point"}}