{"type": "Feature", "id": 28622135, "geometry": {"type": "Point", "coordinates": [135.741684, 35.495831]}, "properties": {"woe:id": 28622135, "woe:parent_id": 28428900, "woe:name": "\u82e5\u72ed\u306e\u5bbf\u30db\u30c6\u30eb\u305b\u304f\u307f\u5c4b", "woe:placetype": 20, "woe:placetype_name": "POI", "woe:lang": "JPN", "iso:country": "JP", "meta:provider": ["geoplanet:7.3.1", "geoplanet:7.3.2", "geoplanet:7.4.0", "geoplanet:7.4.1", "geoplanet:7.5.1", "geoplanet:7.5.2", "geoplanet:7.6.0", "geoplanet:7.8.1", "geoplanet:7.9.0", "geoplanet:7.10.0", "geoplanet:8.0.0", "woeplanet:8.0.0"], "meta:indexed": "2020-08-20T20:47:38.015483", "woe:alias_JPN_V": ["\u305b\u304f\u307f\u5c4b"], "meta:updated": "2020-10-14T12:09:42.772991", "woe:hierarchy": {"continent": 24865671, "country": 23424856, "town": 0, "planet": 1, "county": 0, "suburb": 0, "state": 2345856, "region": 0, "localadmin": 28428900}, "woe:timezone_id": 28350861, "woe:hash": "xn29bvu44qrx", "woe:centroid": [135.741684, 35.495831], "geom:latitude": 35.495831, "geom:longitude": 135.741684, "geom:hash": "xn29bvu44qrx", "woe:latitude": 35.495831, "geom:centroid": [135.741684, 35.495831], "woe:longitude": 135.741684, "woe:repo": "woeplanet-poi-jp", "geom:area": 0.0, "woe:scale": 19}}