{"type": "Feature", "id": 28618941, "properties": {"woe:id": 28618941, "woe:parent_id": 28494533, "woe:name": "\u30a6\u30a7\u30eb\u30b5\u30f3\u30d4\u30a2\u65e5\u7acb", "woe:placetype": 20, "woe:placetype_name": "POI", "woe:lang": "JPN", "iso:country": "JP", "meta:provider": ["geoplanet:7.3.1", "geoplanet:7.3.2", "geoplanet:7.4.0", "geoplanet:7.4.1", "geoplanet:7.5.1", "geoplanet:7.5.2", "geoplanet:7.6.0", "geoplanet:7.8.1", "geoplanet:7.9.0", "geoplanet:7.10.0", "geoplanet:8.0.0", "woeplanet:8.0.0"], "meta:indexed": "2020-08-20T20:47:35.399394", "woe:alias_JPN_V": ["\u30b5\u30f3\u30d4\u30a2\u65e5\u7acb", "\u3046\u3047\u308b\u3055\u3093\u3074\u3042\u3072\u305f\u3061"], "meta:updated": "2020-08-22T02:46:10.730811", "woe:alias_ENG_P": ["Wel Sunpia Hitachi"], "woe:hierarchy": {"continent": 24865671, "country": 23424856, "town": 0, "planet": 1, "county": 0, "suburb": 0, "state": 2345863, "region": 0, "localadmin": 28494533}, "woe:timezone_id": 28350861, "woe:hash": "xn7zxgdj6qpw", "woe:centroid": [140.616867, 36.49477], "geom:latitude": 36.49477, "geom:longitude": 140.616867, "geom:hash": "xn7zxgdj6qpw", "woe:latitude": 36.49477, "geom:centroid": [140.616867, 36.49477], "woe:longitude": 140.616867, "woe:repo": "woeplanet-poi-jp"}, "geometry": {"coordinates": [140.616867, 36.49477], "type": "Point"}}