{"type": "Feature", "id": 28619266, "geometry": {"type": "Point", "coordinates": [139.707474, 36.895309]}, "properties": {"woe:id": 28619266, "woe:parent_id": 28405143, "woe:name": "\u5ddd\u6cbb\u6e29\u6cc9\u5143\u6e6f\u306e\u5bbf\u3089\u3093\u308a\u3087\u3046", "woe:placetype": 20, "woe:placetype_name": "POI", "woe:lang": "JPN", "iso:country": "JP", "meta:provider": ["geoplanet:7.3.1", "geoplanet:7.3.2", "geoplanet:7.4.0", "geoplanet:7.4.1", "geoplanet:7.5.1", "geoplanet:7.5.2", "geoplanet:7.6.0", "geoplanet:7.8.1", "geoplanet:7.9.0", "geoplanet:7.10.0", "geoplanet:8.0.0", "woeplanet:8.0.0"], "meta:indexed": "2020-08-20T20:47:35.661057", "woe:alias_JPN_V": ["\u5143\u6e6f\u5ddd\u6cbb\u6e29\u6cc9\u862d\u7dbe", "\u304b\u308f\u3058\u304a\u3093\u305b\u3093\u3082\u3068\u3086\u306e\u3084\u3069\u3089\u3093\u308a\u3087\u3046"], "meta:updated": "2020-10-14T12:09:58.157413", "woe:alias_ENG_P": ["Kawajionsen Motoyunoyado Ranryo"], "woe:hierarchy": {"continent": 24865671, "country": 23424856, "town": 0, "planet": 1, "county": 0, "suburb": 0, "state": 2345887, "region": 0, "localadmin": 28405143}, "woe:timezone_id": 28350861, "woe:hash": "xne3ghefu055", "woe:centroid": [139.707474, 36.895309], "geom:latitude": 36.895309, "geom:longitude": 139.707474, "geom:hash": "xne3ghefu055", "woe:latitude": 36.895309, "geom:centroid": [139.707474, 36.895309], "woe:longitude": 139.707474, "woe:repo": "woeplanet-poi-jp", "geom:area": 0.0, "woe:scale": 19}}