{"type": "Feature", "id": 28617409, "properties": {"woe:id": 28617409, "woe:parent_id": 28387962, "woe:name": "\u56fd\u6c11\u5bbf\u820e\u3068\u308f\u3060", "woe:placetype": 20, "woe:placetype_name": "POI", "woe:lang": "JPN", "iso:country": "JP", "meta:provider": ["geoplanet:7.3.1", "geoplanet:7.3.2", "geoplanet:7.4.0", "geoplanet:7.4.1", "geoplanet:7.5.1", "geoplanet:7.5.2", "geoplanet:7.6.0", "geoplanet:7.8.1", "geoplanet:7.9.0", "geoplanet:7.10.0", "geoplanet:8.0.0", "woeplanet:8.0.0"], "meta:indexed": "2020-08-20T20:47:34.180564", "woe:alias_JPN_V": ["\u3053\u304f\u307f\u3093\u3057\u3085\u304f\u3057\u3083\u3068\u308f\u3060"], "meta:updated": "2020-08-22T02:46:10.187685", "woe:alias_ENG_P": ["Publice Hostel Towada"], "woe:hierarchy": {"continent": 24865671, "country": 23424856, "town": 0, "planet": 1, "county": 0, "suburb": 0, "state": 2345853, "region": 0, "localadmin": 28387962}, "woe:timezone_id": 28350861, "woe:hash": "xphnncy0cz0y", "woe:centroid": [140.929947, 40.439468], "geom:latitude": 40.439468, "geom:longitude": 140.929947, "geom:hash": "xphnncy0cz0y", "woe:latitude": 40.439468, "geom:centroid": [140.929947, 40.439468], "woe:longitude": 140.929947, "woe:repo": "woeplanet-poi-jp"}, "geometry": {"coordinates": [140.929947, 40.439468], "type": "Point"}}