{"type": "Feature", "id": 28620674, "properties": {"woe:id": 28620674, "woe:parent_id": 28414914, "woe:name": "\u7acb\u5ddd\u30ef\u30b7\u30f3\u30c8\u30f3\u30db\u30c6\u30eb", "woe:placetype": 20, "woe:placetype_name": "POI", "woe:lang": "JPN", "iso:country": "JP", "meta:provider": ["geoplanet:7.3.1", "geoplanet:7.3.2", "geoplanet:7.4.0", "geoplanet:7.4.1", "geoplanet:7.5.1", "geoplanet:7.5.2", "geoplanet:7.6.0", "geoplanet:7.8.1", "geoplanet:7.9.0", "geoplanet:7.10.0", "geoplanet:8.0.0", "woeplanet:8.0.0"], "meta:indexed": "2020-08-20T20:47:36.846554", "woe:alias_JPN_V": ["\u305f\u3061\u304b\u308f\u308f\u3057\u3093\u3068\u3093\u307b\u3066\u308b"], "meta:updated": "2020-08-22T02:46:11.529811", "woe:alias_ENG_P": ["Tachikawa Washington Hotel"], "woe:hierarchy": {"continent": 24865671, "country": 23424856, "town": 0, "planet": 1, "county": 0, "suburb": 0, "state": 2345889, "region": 0, "localadmin": 28414914}, "woe:timezone_id": 28350861, "woe:hash": "xn75h6keg4nw", "woe:centroid": [139.411835, 35.696609], "geom:latitude": 35.696609, "geom:longitude": 139.411835, "geom:hash": "xn75h6keg4nw", "woe:latitude": 35.696609, "geom:centroid": [139.411835, 35.696609], "woe:longitude": 139.411835, "woe:repo": "woeplanet-poi-jp"}, "geometry": {"coordinates": [139.411835, 35.696609], "type": "Point"}}