{"type": "Feature", "id": 28618200, "geometry": {"type": "Point", "coordinates": [140.302063, 38.192219]}, "properties": {"woe:id": 28618200, "woe:parent_id": 28396169, "woe:name": "\u6804\u306e\u5bbf\u4e00\u967d\u9928", "woe:placetype": 20, "woe:placetype_name": "POI", "woe:lang": "JPN", "iso:country": "JP", "meta:provider": ["geoplanet:7.3.1", "geoplanet:7.3.2", "geoplanet:7.4.0", "geoplanet:7.4.1", "geoplanet:7.5.1", "geoplanet:7.5.2", "geoplanet:7.6.0", "geoplanet:7.8.1", "geoplanet:7.9.0", "geoplanet:7.10.0", "geoplanet:8.0.0", "woeplanet:8.0.0"], "meta:indexed": "2020-08-20T20:47:34.788627", "woe:alias_JPN_V": ["\u3055\u304b\u3048\u306e\u3084\u3069\u3044\u3061\u3088\u3046\u304b\u3093"], "meta:updated": "2020-10-14T12:09:45.128168", "woe:alias_ENG_P": ["Sakae No Yado Ichiyokan"], "woe:hierarchy": {"continent": 24865671, "country": 23424856, "town": 0, "planet": 1, "county": 0, "suburb": 0, "state": 2345893, "region": 0, "localadmin": 28396169}, "woe:timezone_id": 28350861, "woe:hash": "xngc28svg18s", "woe:centroid": [140.302063, 38.192219], "geom:latitude": 38.192219, "geom:longitude": 140.302063, "geom:hash": "xngc28svg18s", "woe:latitude": 38.192219, "geom:centroid": [140.302063, 38.192219], "woe:longitude": 140.302063, "woe:repo": "woeplanet-poi-jp", "geom:area": 0.0, "woe:scale": 19}}