{"type": "Feature", "id": 28620440, "properties": {"woe:id": 28620440, "woe:parent_id": 1109119, "woe:name": "\u30db\u30c6\u30eb\u30b5\u30c8\u30fc\u6771\u4eac", "woe:placetype": 20, "woe:placetype_name": "POI", "woe:lang": "JPN", "iso:country": "JP", "meta:provider": ["geoplanet:7.3.1", "geoplanet:7.3.2", "geoplanet:7.4.0", "geoplanet:7.4.1", "geoplanet:7.5.1", "geoplanet:7.5.2", "geoplanet:7.6.0", "geoplanet:7.8.1", "geoplanet:7.9.0", "geoplanet:7.10.0", "geoplanet:8.0.0", "woeplanet:8.0.0"], "meta:indexed": "2020-08-20T20:47:36.661937", "woe:alias_JPN_V": ["\u307b\u3066\u308b\u3055\u3068\u30fc\u3068\u3046\u304d\u3087\u3046"], "meta:updated": "2020-08-22T02:46:11.420955", "woe:alias_ENG_P": ["Hotel Sato Tokyo"], "woe:hierarchy": {"continent": 24865671, "country": 23424856, "town": 0, "planet": 1, "county": 15015397, "suburb": 0, "state": 2345889, "region": 0, "localadmin": 1109119}, "woe:timezone_id": 28350861, "woe:hash": "xn77h5wg7wpw", "woe:centroid": [139.755524, 35.703411], "geom:latitude": 35.703411, "geom:longitude": 139.755524, "geom:hash": "xn77h5wg7wpw", "woe:latitude": 35.703411, "geom:centroid": [139.755524, 35.703411], "woe:longitude": 139.755524, "woe:repo": "woeplanet-poi-jp"}, "geometry": {"coordinates": [139.755524, 35.703411], "type": "Point"}}