{"type": "Feature", "id": 28618776, "geometry": {"type": "Point", "coordinates": [140.359375, 37.605309]}, "properties": {"woe:id": 28618776, "woe:parent_id": 28399623, "woe:name": "\u6adf\u5e73\u30db\u30c6\u30eb", "woe:placetype": 20, "woe:placetype_name": "POI", "woe:lang": "JPN", "iso:country": "JP", "meta:provider": ["geoplanet:7.3.1", "geoplanet:7.3.2", "geoplanet:7.4.0", "geoplanet:7.4.1", "geoplanet:7.5.1", "geoplanet:7.5.2", "geoplanet:7.6.0", "geoplanet:7.8.1", "geoplanet:7.9.0", "geoplanet:7.10.0", "geoplanet:8.0.0", "woeplanet:8.0.0"], "meta:indexed": "2020-08-20T20:47:35.255066", "woe:alias_JPN_V": ["\u304f\u306c\u304e\u3060\u3044\u3089\u307b\u3066\u308b"], "meta:updated": "2020-10-14T12:09:46.145890", "woe:alias_ENG_P": ["Kunugidaira Hotel"], "woe:hierarchy": {"continent": 24865671, "country": 23424856, "town": 0, "planet": 1, "county": 0, "suburb": 0, "state": 2345858, "region": 0, "localadmin": 28399623}, "woe:timezone_id": 28350861, "woe:hash": "xnevcvydf3xt", "woe:centroid": [140.359375, 37.605309], "geom:latitude": 37.605309, "geom:longitude": 140.359375, "geom:hash": "xnevcvydf3xt", "woe:latitude": 37.605309, "geom:centroid": [140.359375, 37.605309], "woe:longitude": 140.359375, "woe:repo": "woeplanet-poi-jp", "geom:area": 0.0, "woe:scale": 19}}