{"type": "Feature", "id": 28618793, "properties": {"woe:id": 28618793, "woe:parent_id": 28400429, "woe:name": "\u30db\u30c6\u30eb\u6d17\u5fc3\u4ead", "woe:placetype": 20, "woe:placetype_name": "POI", "woe:lang": "JPN", "iso:country": "JP", "meta:provider": ["geoplanet:7.3.1", "geoplanet:7.3.2", "geoplanet:7.4.0", "geoplanet:7.4.1", "geoplanet:7.5.1", "geoplanet:7.5.2", "geoplanet:7.6.0", "geoplanet:7.8.1", "geoplanet:7.9.0", "geoplanet:7.10.0", "geoplanet:8.0.0", "woeplanet:8.0.0"], "meta:indexed": "2020-08-20T20:47:35.270242", "woe:alias_JPN_V": ["\u307b\u3066\u308b\u305b\u3093\u3057\u3093\u3066\u3044"], "meta:updated": "2020-08-22T02:46:10.676621", "woe:alias_ENG_P": ["Hotel Sensintei"], "woe:hierarchy": {"continent": 24865671, "country": 23424856, "town": 0, "planet": 1, "county": 24853648, "suburb": 0, "state": 2345858, "region": 0, "localadmin": 28400429}, "woe:timezone_id": 28350861, "woe:hash": "xnekprwzybvt", "woe:centroid": [139.898483, 37.308159], "geom:latitude": 37.308159, "geom:longitude": 139.898483, "geom:hash": "xnekprwzybvt", "woe:latitude": 37.308159, "geom:centroid": [139.898483, 37.308159], "woe:longitude": 139.898483, "woe:repo": "woeplanet-poi-jp"}, "geometry": {"coordinates": [139.898483, 37.308159], "type": "Point"}}