{"type": "Feature", "id": 28620671, "geometry": {"type": "Point", "coordinates": [139.409897, 35.697571]}, "properties": {"woe:id": 28620671, "woe:parent_id": 28414914, "woe:name": "\u30d3\u30b8\u30cd\u30b9\u30db\u30c6\u30eb\u5b89\u5ddd", "woe:placetype": 20, "woe:placetype_name": "POI", "woe:lang": "JPN", "iso:country": "JP", "meta:provider": ["geoplanet:7.3.1", "geoplanet:7.3.2", "geoplanet:7.4.0", "geoplanet:7.4.1", "geoplanet:7.5.1", "geoplanet:7.5.2", "geoplanet:7.6.0", "geoplanet:7.8.1", "geoplanet:7.9.0", "geoplanet:7.10.0", "geoplanet:8.0.0", "woeplanet:8.0.0"], "meta:indexed": "2020-08-20T20:47:36.844214", "woe:alias_JPN_V": ["\u3073\u3058\u306d\u3059\u307b\u3066\u308b\u3084\u3059\u304b\u308f"], "meta:updated": "2020-10-14T12:09:52.503912", "woe:alias_ENG_P": ["Business Hotel Yasukawa"], "woe:hierarchy": {"continent": 24865671, "country": 23424856, "town": 0, "planet": 1, "county": 0, "suburb": 0, "state": 2345889, "region": 0, "localadmin": 28414914}, "woe:timezone_id": 28350861, "woe:hash": "xn75h6e1qj99", "woe:centroid": [139.409897, 35.697571], "geom:latitude": 35.697571, "geom:longitude": 139.409897, "geom:hash": "xn75h6e1qj99", "woe:latitude": 35.697571, "geom:centroid": [139.409897, 35.697571], "woe:longitude": 139.409897, "woe:repo": "woeplanet-poi-jp", "geom:area": 0.0, "woe:scale": 19}}