{"type": "Feature", "id": 28618672, "geometry": {"type": "Point", "coordinates": [140.846848, 37.010719]}, "properties": {"woe:id": 28618672, "woe:parent_id": 28398723, "woe:name": "\u3044\u308f\u304d\u6e6f\u672c\u89b3\u5149\u30db\u30c6\u30eb\u904a\u6e6f\u4ead", "woe:placetype": 20, "woe:placetype_name": "POI", "woe:lang": "JPN", "iso:country": "JP", "meta:provider": ["geoplanet:7.3.1", "geoplanet:7.3.2", "geoplanet:7.4.0", "geoplanet:7.4.1", "geoplanet:7.5.1", "geoplanet:7.5.2", "geoplanet:7.6.0", "geoplanet:7.8.1", "geoplanet:7.9.0", "geoplanet:7.10.0", "geoplanet:8.0.0", "woeplanet:8.0.0"], "meta:indexed": "2020-08-20T20:47:35.165580", "woe:alias_JPN_V": ["\u3044\u308f\u304d\u3086\u3082\u3068\u304b\u3093\u3053\u3046\u307b\u3066\u308b\u3086\u3046\u3086\u3046\u3066\u3044"], "meta:updated": "2020-10-14T12:09:44.414656", "woe:alias_ENG_P": ["Iwaki Yumoto Kanko Hotel Yuuyuutei"], "woe:hierarchy": {"continent": 24865671, "country": 23424856, "town": 0, "planet": 1, "county": 0, "suburb": 0, "state": 2345858, "region": 0, "localadmin": 28398723}, "woe:timezone_id": 28350861, "woe:hash": "xns4t19e16jf", "woe:centroid": [140.846848, 37.010719], "geom:latitude": 37.010719, "geom:longitude": 140.846848, "geom:hash": "xns4t19e16jf", "woe:latitude": 37.010719, "geom:centroid": [140.846848, 37.010719], "woe:longitude": 140.846848, "woe:repo": "woeplanet-poi-jp", "geom:area": 0.0, "woe:scale": 19}}