{"type": "Feature", "id": 28619983, "properties": {"woe:id": 28619983, "woe:parent_id": 28410541, "woe:name": "\u4eac\u6210\u30db\u30c6\u30eb\u30df\u30e9\u30de\u30fc\u30ec", "woe:placetype": 20, "woe:placetype_name": "POI", "woe:lang": "JPN", "iso:country": "JP", "meta:provider": ["geoplanet:7.3.1", "geoplanet:7.3.2", "geoplanet:7.4.0", "geoplanet:7.4.1", "geoplanet:7.5.1", "geoplanet:7.5.2", "geoplanet:7.6.0", "geoplanet:7.8.1", "geoplanet:7.9.0", "geoplanet:7.10.0", "geoplanet:8.0.0", "woeplanet:8.0.0"], "meta:indexed": "2020-08-20T20:47:36.325512", "woe:alias_JPN_V": ["\u3051\u3044\u305b\u3044\u307b\u3066\u308b\u307f\u3089\u307e\u30fc\u308c"], "meta:updated": "2020-08-22T02:46:11.213248", "woe:alias_ENG_P": ["Keisei Hotel Miramare"], "woe:hierarchy": {"continent": 24865671, "country": 23424856, "town": 0, "planet": 1, "county": 15015398, "suburb": 0, "state": 2345854, "region": 0, "localadmin": 28410541}, "woe:timezone_id": 28350861, "woe:hash": "xn7ds6nvmg7t", "woe:centroid": [140.118164, 35.607609], "geom:latitude": 35.607609, "geom:longitude": 140.118164, "geom:hash": "xn7ds6nvmg7t", "woe:latitude": 35.607609, "geom:centroid": [140.118164, 35.607609], "woe:longitude": 140.118164, "woe:repo": "woeplanet-poi-jp"}, "geometry": {"coordinates": [140.118164, 35.607609], "type": "Point"}}