{"type": "Feature", "id": 28621081, "properties": {"woe:id": 28621081, "woe:parent_id": 28417510, "woe:name": "\u5927\u6edd\u30db\u30c6\u30eb", "woe:placetype": 20, "woe:placetype_name": "POI", "woe:lang": "JPN", "iso:country": "JP", "meta:provider": ["geoplanet:7.3.1", "geoplanet:7.3.2", "geoplanet:7.4.0", "geoplanet:7.4.1", "geoplanet:7.5.1", "geoplanet:7.5.2", "geoplanet:7.6.0", "geoplanet:7.8.1", "geoplanet:7.9.0", "geoplanet:7.10.0", "geoplanet:8.0.0", "woeplanet:8.0.0"], "meta:indexed": "2020-08-20T20:47:37.177614", "woe:alias_JPN_V": ["\u304a\u304a\u305f\u304d\u307b\u3066\u308b"], "meta:updated": "2020-08-22T02:46:11.751050", "woe:alias_ENG_P": ["Otaki Hotel"], "woe:hierarchy": {"continent": 24865671, "country": 23424856, "town": 0, "planet": 1, "county": 24857810, "suburb": 0, "state": 2345868, "region": 0, "localadmin": 28417510}, "woe:timezone_id": 28350861, "woe:hash": "xn4zux63wfmz", "woe:centroid": [139.068329, 35.152401], "geom:latitude": 35.152401, "geom:longitude": 139.068329, "geom:hash": "xn4zux63wfmz", "woe:latitude": 35.152401, "geom:centroid": [139.068329, 35.152401], "woe:longitude": 139.068329, "woe:repo": "woeplanet-poi-jp"}, "geometry": {"coordinates": [139.068329, 35.152401], "type": "Point"}}