{"type": "Feature", "id": 28617259, "properties": {"woe:id": 28617259, "woe:parent_id": 28386742, "woe:name": "\u5ddd\u6e6f\u30db\u30c6\u30eb\u30d7\u30e9\u30b6", "woe:placetype": 20, "woe:placetype_name": "POI", "woe:lang": "JPN", "iso:country": "JP", "meta:provider": ["geoplanet:7.3.1", "geoplanet:7.3.2", "geoplanet:7.4.0", "geoplanet:7.4.1", "geoplanet:7.5.1", "geoplanet:7.5.2", "geoplanet:7.6.0", "geoplanet:7.8.1", "geoplanet:7.9.0", "geoplanet:7.10.0", "geoplanet:8.0.0", "woeplanet:8.0.0"], "meta:indexed": "2020-08-20T20:47:34.046749", "woe:alias_JPN_V": ["\u304b\u308f\u3086\u307b\u3066\u308b\u3077\u3089\u3056"], "meta:updated": "2020-08-22T02:46:10.133426", "woe:alias_ENG_P": ["Kawayu Hotel Plaza"], "woe:hierarchy": {"continent": 24865671, "country": 23424856, "town": 0, "planet": 1, "county": 24853927, "suburb": 0, "state": 7153351, "region": 0, "localadmin": 28386742}, "woe:timezone_id": 28350861, "woe:hash": "xpy8nxzrdwj1", "woe:centroid": [144.43634, 43.637642], "geom:latitude": 43.637642, "geom:longitude": 144.43634, "geom:hash": "xpy8nxzrdwj1", "woe:latitude": 43.637642, "geom:centroid": [144.43634, 43.637642], "woe:longitude": 144.43634, "woe:repo": "woeplanet-poi-jp"}, "geometry": {"coordinates": [144.43634, 43.637642], "type": "Point"}}