{"type": "Feature", "id": 28621960, "properties": {"woe:id": 28621960, "woe:parent_id": 28427212, "woe:name": "\u305f\u3061\u3070\u306a\u56db\u5b63\u4ead", "woe:placetype": 20, "woe:placetype_name": "POI", "woe:lang": "JPN", "iso:country": "JP", "meta:provider": ["geoplanet:7.3.1", "geoplanet:7.3.2", "geoplanet:7.4.0", "geoplanet:7.4.1", "geoplanet:7.5.1", "geoplanet:7.5.2", "geoplanet:7.6.0", "geoplanet:7.8.1", "geoplanet:7.9.0", "geoplanet:7.10.0", "geoplanet:8.0.0", "woeplanet:8.0.0"], "meta:indexed": "2020-08-20T20:47:37.887780", "meta:updated": "2020-08-22T02:46:12.149971", "woe:hierarchy": {"continent": 24865671, "country": 23424856, "town": 0, "planet": 1, "county": 0, "suburb": 0, "state": 2345864, "region": 0, "localadmin": 28427212}, "woe:timezone_id": 28350861, "woe:hash": "xn2yqync4kcy", "woe:centroid": [136.360687, 36.28804], "geom:latitude": 36.28804, "geom:longitude": 136.360687, "geom:hash": "xn2yqync4kcy", "woe:latitude": 36.28804, "geom:centroid": [136.360687, 36.28804], "woe:longitude": 136.360687, "woe:repo": "woeplanet-poi-jp"}, "geometry": {"coordinates": [136.360687, 36.28804], "type": "Point"}}