{"type": "Feature", "id": 28618955, "geometry": {"type": "Point", "coordinates": [140.714157, 36.663368]}, "properties": {"woe:id": 28618955, "woe:parent_id": 28401881, "woe:name": "\u56fd\u6c11\u5bbf\u820e\u9d5c\u306e\u5cac", "woe:placetype": 20, "woe:placetype_name": "POI", "woe:lang": "JPN", "iso:country": "JP", "meta:provider": ["geoplanet:7.3.1", "geoplanet:7.3.2", "geoplanet:7.4.0", "geoplanet:7.4.1", "geoplanet:7.5.1", "geoplanet:7.5.2", "geoplanet:7.6.0", "geoplanet:7.8.1", "geoplanet:7.9.0", "geoplanet:7.10.0", "geoplanet:8.0.0", "woeplanet:8.0.0"], "meta:indexed": "2020-08-20T20:47:35.411244", "woe:alias_JPN_V": ["\u3053\u304f\u307f\u3093\u3057\u3085\u304f\u3057\u3083\u3046\u306e\u307f\u3055\u304d"], "meta:updated": "2020-10-14T12:09:46.848635", "woe:alias_ENG_P": ["Public Hostel Unomisaki"], "woe:hierarchy": {"continent": 24865671, "country": 23424856, "town": 0, "planet": 1, "county": 0, "suburb": 0, "state": 2345863, "region": 0, "localadmin": 28401881}, "woe:timezone_id": 28350861, "woe:hash": "xns0d42gte0m", "woe:centroid": [140.714157, 36.663368], "geom:latitude": 36.663368, "geom:longitude": 140.714157, "geom:hash": "xns0d42gte0m", "woe:latitude": 36.663368, "geom:centroid": [140.714157, 36.663368], "woe:longitude": 140.714157, "woe:repo": "woeplanet-poi-jp", "geom:area": 0.0, "woe:scale": 19}}