{"type": "Feature", "id": 28619572, "geometry": {"type": "Point", "coordinates": [138.923096, 36.502041]}, "properties": {"woe:id": 28619572, "woe:parent_id": 28407036, "woe:name": "\u30db\u30c6\u30eb\u30cb\u30e5\u30fc\u4f0a\u9999\u4fdd", "woe:placetype": 20, "woe:placetype_name": "POI", "woe:lang": "JPN", "iso:country": "JP", "meta:provider": ["geoplanet:7.3.1", "geoplanet:7.3.2", "geoplanet:7.4.0", "geoplanet:7.4.1", "geoplanet:7.5.1", "geoplanet:7.5.2", "geoplanet:7.6.0", "geoplanet:7.8.1", "geoplanet:7.9.0", "geoplanet:7.10.0", "geoplanet:8.0.0", "woeplanet:8.0.0"], "meta:indexed": "2020-08-20T20:47:35.911413", "woe:alias_JPN_V": ["\u307b\u3066\u308b\u306b\u3085\u30fc\u3044\u304b\u307b"], "meta:updated": "2020-10-14T12:09:45.189504", "woe:alias_ENG_P": ["Hotel New Ikaho"], "woe:hierarchy": {"continent": 24865671, "country": 23424856, "town": 0, "planet": 1, "county": 0, "suburb": 0, "state": 2345860, "region": 0, "localadmin": 28407036}, "woe:timezone_id": 28350861, "woe:hash": "xn6z9kbxyc8k", "woe:centroid": [138.923096, 36.502041], "geom:latitude": 36.502041, "geom:longitude": 138.923096, "geom:hash": "xn6z9kbxyc8k", "woe:latitude": 36.502041, "geom:centroid": [138.923096, 36.502041], "woe:longitude": 138.923096, "woe:repo": "woeplanet-poi-jp", "geom:area": 0.0, "woe:scale": 19}}