{"type": "Feature", "id": 28620391, "properties": {"woe:id": 28620391, "woe:parent_id": 28414057, "woe:name": "\u65b0\u5bbf\u30b7\u30c6\u30a3\u30db\u30c6\u30eb\u30ed\u30f3\u30b9\u30bf\u30fc", "woe:placetype": 20, "woe:placetype_name": "POI", "woe:lang": "JPN", "iso:country": "JP", "meta:provider": ["geoplanet:7.3.1", "geoplanet:7.3.2", "geoplanet:7.4.0", "geoplanet:7.4.1", "geoplanet:7.5.1", "geoplanet:7.5.2", "geoplanet:7.6.0", "geoplanet:7.8.1", "geoplanet:7.9.0", "geoplanet:7.10.0", "geoplanet:8.0.0", "woeplanet:8.0.0"], "meta:indexed": "2020-08-20T20:47:36.629261", "woe:alias_JPN_V": ["\u30b7\u30c6\u30a3\u30db\u30c6\u30eb\u30ed\u30f3\u30b9\u30bf\u30fc", "\u3057\u3093\u3058\u3085\u304f\u3057\u3066\u3043\u307b\u3066\u308b\u308d\u3093\u3059\u305f\u30fc"], "meta:updated": "2020-08-22T02:46:11.399768", "woe:alias_ENG_P": ["Shinjuku City Hotel Lonestar"], "woe:hierarchy": {"continent": 24865671, "country": 23424856, "town": 0, "planet": 1, "county": 15015378, "suburb": 0, "state": 2345889, "region": 0, "localadmin": 28414057}, "woe:timezone_id": 28350861, "woe:hash": "xn7751k0w3he", "woe:centroid": [139.707916, 35.690552], "geom:latitude": 35.690552, "geom:longitude": 139.707916, "geom:hash": "xn7751k0w3he", "woe:latitude": 35.690552, "geom:centroid": [139.707916, 35.690552], "woe:longitude": 139.707916, "woe:repo": "woeplanet-poi-jp"}, "geometry": {"coordinates": [139.707916, 35.690552], "type": "Point"}}