{"type": "Feature", "id": 28620462, "properties": {"woe:id": 28620462, "woe:parent_id": 28414148, "woe:name": "\uff2e\uff25\uff37\u4f0a\u8c46\u30db\u30c6\u30eb", "woe:placetype": 20, "woe:placetype_name": "POI", "woe:lang": "JPN", "iso:country": "JP", "meta:provider": ["geoplanet:7.3.1", "geoplanet:7.3.2", "geoplanet:7.4.0", "geoplanet:7.4.1", "geoplanet:7.5.1", "geoplanet:7.5.2", "geoplanet:7.6.0", "geoplanet:7.8.1", "geoplanet:7.9.0", "geoplanet:7.10.0", "geoplanet:8.0.0", "woeplanet:8.0.0"], "meta:indexed": "2020-08-20T20:47:36.677483", "woe:alias_JPN_V": ["\u306b\u3085\u30fc\u3044\u305a\u307b\u3066\u308b"], "meta:updated": "2020-08-22T02:46:11.431291", "woe:alias_ENG_P": ["New Izu Hotel"], "woe:hierarchy": {"continent": 24865671, "country": 23424856, "town": 0, "planet": 1, "county": 15015401, "suburb": 0, "state": 2345889, "region": 0, "localadmin": 28414148}, "woe:timezone_id": 28350861, "woe:hash": "xn77hub4ff75", "woe:centroid": [139.779175, 35.710171], "geom:latitude": 35.710171, "geom:longitude": 139.779175, "geom:hash": "xn77hub4ff75", "woe:latitude": 35.710171, "geom:centroid": [139.779175, 35.710171], "woe:longitude": 139.779175, "woe:repo": "woeplanet-poi-jp"}, "geometry": {"coordinates": [139.779175, 35.710171], "type": "Point"}}