{"type": "Feature", "id": 28617611, "properties": {"woe:id": 28617611, "woe:parent_id": 28389999, "woe:name": "\u9808\u5ddd\u9ad8\u539f\u6e29\u6cc9", "woe:placetype": 20, "woe:placetype_name": "POI", "woe:lang": "JPN", "iso:country": "JP", "meta:provider": ["geoplanet:7.3.1", "geoplanet:7.3.2", "geoplanet:7.4.0", "geoplanet:7.4.1", "geoplanet:7.5.1", "geoplanet:7.5.2", "geoplanet:7.6.0", "geoplanet:7.8.1", "geoplanet:7.9.0", "geoplanet:7.10.0", "geoplanet:8.0.0", "woeplanet:8.0.0"], "meta:indexed": "2020-08-20T20:47:34.336312", "woe:alias_JPN_V": ["\u3059\u304b\u308f\u3053\u3046\u3052\u3093\u304a\u3093\u305b\u3093"], "meta:updated": "2020-08-22T02:46:10.258183", "woe:alias_ENG_P": ["Sukawakougen Onsen"], "woe:hierarchy": {"continent": 24865671, "country": 23424856, "town": 0, "planet": 1, "county": 0, "suburb": 0, "state": 2345865, "region": 0, "localadmin": 28389999}, "woe:timezone_id": 28350861, "woe:hash": "xnujg21bgxr9", "woe:centroid": [140.770386, 38.97966], "geom:latitude": 38.97966, "geom:longitude": 140.770386, "geom:hash": "xnujg21bgxr9", "woe:latitude": 38.97966, "geom:centroid": [140.770386, 38.97966], "woe:longitude": 140.770386, "woe:repo": "woeplanet-poi-jp"}, "geometry": {"coordinates": [140.770386, 38.97966], "type": "Point"}}