{"type": "Feature", "id": 28620283, "properties": {"woe:id": 28620283, "woe:parent_id": 28413993, "woe:name": "\u30db\u30c6\u30eb\u30b5\u30fc\u30c9\u30cb\u30af\u30b9\u6771\u4eac", "woe:placetype": 20, "woe:placetype_name": "POI", "woe:lang": "JPN", "iso:country": "JP", "meta:provider": ["geoplanet:7.3.1", "geoplanet:7.3.2", "geoplanet:7.4.0", "geoplanet:7.4.1", "geoplanet:7.5.1", "geoplanet:7.5.2", "geoplanet:7.6.0", "geoplanet:7.8.1", "geoplanet:7.9.0", "geoplanet:7.10.0", "geoplanet:8.0.0", "woeplanet:8.0.0"], "meta:indexed": "2020-08-20T20:47:36.555456", "woe:alias_JPN_V": ["\u30b5\u30fc\u30c9\u30cb\u30af\u30b9\u6771\u4eac", "\u307b\u3066\u308b\u3055\u30fc\u3069\u306b\u304f\u3059\u3068\u3046\u304d\u3087\u3046"], "meta:updated": "2020-08-22T02:46:11.352552", "woe:alias_ENG_P": ["Hotel Sardonyx Tokyo"], "woe:hierarchy": {"continent": 24865671, "country": 23424856, "town": 0, "planet": 1, "county": 15015500, "suburb": 0, "state": 2345889, "region": 0, "localadmin": 28413993}, "woe:timezone_id": 28350861, "woe:hash": "xn76uwz87vt1", "woe:centroid": [139.778534, 35.6768], "geom:latitude": 35.6768, "geom:longitude": 139.778534, "geom:hash": "xn76uwz87vt1", "woe:latitude": 35.6768, "geom:centroid": [139.778534, 35.6768], "woe:longitude": 139.778534, "woe:repo": "woeplanet-poi-jp"}, "geometry": {"coordinates": [139.778534, 35.6768], "type": "Point"}}