{"type": "Feature", "id": 28622836, "properties": {"woe:id": 28622836, "woe:parent_id": 28431872, "woe:name": "\u98ef\u7530\u89b3\u5149\u30db\u30c6\u30eb\u3088\u3057\u4e43\u4ead", "woe:placetype": 20, "woe:placetype_name": "POI", "woe:lang": "JPN", "iso:country": "JP", "meta:provider": ["geoplanet:7.3.1", "geoplanet:7.3.2", "geoplanet:7.4.0", "geoplanet:7.4.1", "geoplanet:7.5.1", "geoplanet:7.5.2", "geoplanet:7.6.0", "geoplanet:7.8.1", "geoplanet:7.9.0", "geoplanet:7.10.0", "geoplanet:8.0.0", "woeplanet:8.0.0"], "meta:indexed": "2020-08-20T20:47:38.555806", "woe:alias_JPN_V": ["\u98ef\u7530\u89b3\u5149\u30db\u30c6\u30eb", "\u3044\u3044\u3060\u304b\u3093\u3053\u3046\u307b\u3066\u308b\u3088\u3057\u306e\u3066\u3044"], "meta:updated": "2020-08-22T02:46:12.545400", "woe:alias_ENG_P": ["Iida Kanko Hotel Yoshinotei"], "woe:hierarchy": {"continent": 24865671, "country": 23424856, "town": 0, "planet": 1, "county": 0, "suburb": 0, "state": 2345875, "region": 0, "localadmin": 28431872}, "woe:timezone_id": 28350861, "woe:hash": "xn61bg79mswr", "woe:centroid": [137.85051, 35.48196], "geom:latitude": 35.48196, "geom:longitude": 137.85051, "geom:hash": "xn61bg79mswr", "woe:latitude": 35.48196, "geom:centroid": [137.85051, 35.48196], "woe:longitude": 137.85051, "woe:repo": "woeplanet-poi-jp"}, "geometry": {"coordinates": [137.85051, 35.48196], "type": "Point"}}