{"type": "Feature", "id": 28616508, "geometry": {"type": "Point", "coordinates": [141.316574, 43.054649]}, "properties": {"woe:id": 28616508, "woe:parent_id": 28379447, "woe:name": "\u30db\u30c6\u30eb\u795e\u5bae", "woe:placetype": 20, "woe:placetype_name": "POI", "woe:lang": "JPN", "iso:country": "JP", "meta:provider": ["geoplanet:7.3.1", "geoplanet:7.3.2", "geoplanet:7.4.0", "geoplanet:7.4.1", "geoplanet:7.5.1", "geoplanet:7.5.2", "geoplanet:7.6.0", "geoplanet:7.8.1", "geoplanet:7.9.0", "geoplanet:7.10.0", "geoplanet:8.0.0", "woeplanet:8.0.0"], "meta:indexed": "2020-08-20T20:47:33.380431", "meta:updated": "2020-10-14T12:09:50.929938", "woe:hierarchy": {"continent": 24865671, "country": 23424856, "town": 0, "planet": 1, "county": 15015394, "suburb": 0, "state": 7153351, "region": 0, "localadmin": 28379447}, "woe:timezone_id": 28350861, "woe:hash": "xpskztzedb6c", "woe:centroid": [141.316574, 43.054649], "geom:latitude": 43.054649, "geom:longitude": 141.316574, "geom:hash": "xpskztzedb6c", "woe:latitude": 43.054649, "geom:centroid": [141.316574, 43.054649], "woe:longitude": 141.316574, "woe:repo": "woeplanet-poi-jp", "geom:area": 0.0, "woe:scale": 19}}