{"type": "Feature", "id": 28621554, "geometry": {"type": "Point", "coordinates": [139.580078, 38.08403]}, "properties": {"woe:id": 28621554, "woe:parent_id": 28422781, "woe:name": "\u7c73\u6ca2\u5c4b\u6c34\u7434\u4ead", "woe:placetype": 20, "woe:placetype_name": "POI", "woe:lang": "JPN", "iso:country": "JP", "meta:provider": ["geoplanet:7.3.1", "geoplanet:7.3.2", "geoplanet:7.4.0", "geoplanet:7.4.1", "geoplanet:7.5.1", "geoplanet:7.5.2", "geoplanet:7.6.0", "geoplanet:7.8.1", "geoplanet:7.9.0", "geoplanet:7.10.0", "geoplanet:8.0.0", "woeplanet:8.0.0"], "meta:indexed": "2020-08-20T20:47:37.575593", "woe:alias_JPN_V": ["\u3088\u306d\u3056\u308f\u3084\u3059\u3044\u304d\u3093\u3066\u3044"], "meta:updated": "2020-10-14T12:09:59.045222", "woe:alias_ENG_P": ["Yonezawaya Suikintei"], "woe:hierarchy": {"continent": 24865671, "country": 23424856, "town": 0, "planet": 1, "county": 24857453, "suburb": 0, "state": 2345878, "region": 0, "localadmin": 28422781}, "woe:timezone_id": 28350861, "woe:hash": "xng28hzpe99x", "woe:centroid": [139.580078, 38.08403], "geom:latitude": 38.08403, "geom:longitude": 139.580078, "geom:hash": "xng28hzpe99x", "woe:latitude": 38.08403, "geom:centroid": [139.580078, 38.08403], "woe:longitude": 139.580078, "woe:repo": "woeplanet-poi-jp", "geom:area": 0.0, "woe:scale": 19}}