{"type": "Feature", "id": 28616566, "properties": {"woe:id": 28616566, "woe:parent_id": 28379862, "woe:name": "\u30a2\u30d1\u30db\u30c6\u30eb\uff06\u30ea\u30be\u30fc\u30c8\u672d\u5e4c", "woe:placetype": 20, "woe:placetype_name": "POI", "woe:lang": "JPN", "iso:country": "JP", "meta:provider": ["geoplanet:7.3.1", "geoplanet:7.3.2", "geoplanet:7.4.0", "geoplanet:7.4.1", "geoplanet:7.5.1", "geoplanet:7.5.2", "geoplanet:7.6.0", "geoplanet:7.8.1", "geoplanet:7.9.0", "geoplanet:7.10.0", "geoplanet:8.0.0", "woeplanet:8.0.0"], "meta:indexed": "2020-08-20T20:47:33.425942", "woe:alias_JPN_V": ["\u3042\u3071\u307b\u3066\u308b\u3042\u3093\u3069\u308a\u305e\u30fc\u3068\u3055\u3063\u307d\u308d"], "meta:updated": "2020-08-22T02:46:09.891936", "woe:alias_ENG_P": ["Apa Hotel&resort Sapporo"], "woe:hierarchy": {"continent": 24865671, "country": 23424856, "town": 0, "planet": 1, "county": 1111800, "suburb": 0, "state": 7153351, "region": 0, "localadmin": 28379862}, "woe:timezone_id": 28350861, "woe:hash": "xpss84utz6qb", "woe:centroid": [141.334625, 42.994621], "geom:latitude": 42.994621, "geom:longitude": 141.334625, "geom:hash": "xpss84utz6qb", "woe:latitude": 42.994621, "geom:centroid": [141.334625, 42.994621], "woe:longitude": 141.334625, "woe:repo": "woeplanet-poi-jp"}, "geometry": {"coordinates": [141.334625, 42.994621], "type": "Point"}}