{"type": "Feature", "id": 28616641, "geometry": {"type": "Point", "coordinates": [140.726822, 41.771759]}, "properties": {"woe:id": 28616641, "woe:parent_id": 1116368, "woe:name": "\u6d25\u8efd\u5c4b\u65c5\u9928", "woe:placetype": 20, "woe:placetype_name": "POI", "woe:lang": "JPN", "iso:country": "JP", "meta:provider": ["geoplanet:7.3.1", "geoplanet:7.3.2", "geoplanet:7.4.0", "geoplanet:7.4.1", "geoplanet:7.5.1", "geoplanet:7.5.2", "geoplanet:7.6.0", "geoplanet:7.8.1", "geoplanet:7.9.0", "geoplanet:7.10.0", "geoplanet:8.0.0", "woeplanet:8.0.0"], "meta:indexed": "2020-08-20T20:47:33.486466", "meta:updated": "2020-10-14T12:09:47.745402", "woe:hierarchy": {"continent": 24865671, "country": 23424856, "town": 0, "planet": 1, "county": 0, "suburb": 0, "state": 7153351, "region": 0, "localadmin": 1116368}, "woe:timezone_id": 28350861, "woe:hash": "xpkjdk64hs7b", "woe:centroid": [140.726822, 41.771759], "geom:latitude": 41.771759, "geom:longitude": 140.726822, "geom:hash": "xpkjdk64hs7b", "woe:latitude": 41.771759, "geom:centroid": [140.726822, 41.771759], "woe:longitude": 140.726822, "woe:repo": "woeplanet-poi-jp", "geom:area": 0.0, "woe:scale": 19}}