{"type": "Feature", "id": 28618947, "geometry": {"type": "Point", "coordinates": [140.629959, 36.555828]}, "properties": {"woe:id": 28618947, "woe:parent_id": 28401849, "woe:name": "\u30db\u30c6\u30eb\u30eb\u30fc\u30c8\u30a4\u30f3\u65e5\u7acb\u591a\u8cc0", "woe:placetype": 20, "woe:placetype_name": "POI", "woe:lang": "JPN", "iso:country": "JP", "meta:provider": ["geoplanet:7.3.1", "geoplanet:7.3.2", "geoplanet:7.4.0", "geoplanet:7.4.1", "geoplanet:7.5.1", "geoplanet:7.5.2", "geoplanet:7.6.0", "geoplanet:7.8.1", "geoplanet:7.9.0", "geoplanet:7.10.0", "geoplanet:8.0.0", "woeplanet:8.0.0"], "meta:indexed": "2020-08-20T20:47:35.404522", "woe:alias_JPN_V": ["\u307b\u3066\u308b\u308b\u30fc\u3068\u3044\u3093\u3072\u305f\u3061\u305f\u304c"], "meta:updated": "2020-10-14T12:09:46.851102", "woe:alias_ENG_P": ["Hotel Route Inn Hitachitaga"], "woe:hierarchy": {"continent": 24865671, "country": 23424856, "town": 0, "planet": 1, "county": 0, "suburb": 0, "state": 2345863, "region": 0, "localadmin": 28401849}, "woe:timezone_id": 28350861, "woe:hash": "xnkpbng95s1x", "woe:centroid": [140.629959, 36.555828], "geom:latitude": 36.555828, "geom:longitude": 140.629959, "geom:hash": "xnkpbng95s1x", "woe:latitude": 36.555828, "geom:centroid": [140.629959, 36.555828], "woe:longitude": 140.629959, "woe:repo": "woeplanet-poi-jp", "geom:area": 0.0, "woe:scale": 19}}