{"type": "Feature", "id": 28617407, "geometry": {"type": "Point", "coordinates": [140.893784, 40.431099]}, "properties": {"woe:id": 28617407, "woe:parent_id": 28387962, "woe:name": "\u4f11\u5c4b\u6842\u6708\u4ead", "woe:placetype": 20, "woe:placetype_name": "POI", "woe:lang": "JPN", "iso:country": "JP", "meta:provider": ["geoplanet:7.3.1", "geoplanet:7.3.2", "geoplanet:7.4.0", "geoplanet:7.4.1", "geoplanet:7.5.1", "geoplanet:7.5.2", "geoplanet:7.6.0", "geoplanet:7.8.1", "geoplanet:7.9.0", "geoplanet:7.10.0", "geoplanet:8.0.0", "woeplanet:8.0.0"], "meta:indexed": "2020-08-20T20:47:34.178729", "woe:alias_JPN_V": ["\u3084\u3059\u307f\u3084\u3051\u3044\u3052\u3064\u3066\u3044"], "meta:updated": "2020-10-14T12:09:53.983271", "woe:alias_ENG_P": ["Yasumiya Keigetsutei"], "woe:hierarchy": {"continent": 24865671, "country": 23424856, "town": 0, "planet": 1, "county": 0, "suburb": 0, "state": 2345853, "region": 0, "localadmin": 28387962}, "woe:timezone_id": 28350861, "woe:hash": "xphnn078pp5g", "woe:centroid": [140.893784, 40.431099], "geom:latitude": 40.431099, "geom:longitude": 140.893784, "geom:hash": "xphnn078pp5g", "woe:latitude": 40.431099, "geom:centroid": [140.893784, 40.431099], "woe:longitude": 140.893784, "woe:repo": "woeplanet-poi-jp", "geom:area": 0.0, "woe:scale": 19}}