{"type": "Feature", "id": 28621604, "properties": {"woe:id": 28621604, "woe:parent_id": 28423466, "woe:name": "\u5449\u7fbd\u30cf\u30a4\u30c4", "woe:placetype": 20, "woe:placetype_name": "POI", "woe:lang": "JPN", "iso:country": "JP", "meta:provider": ["geoplanet:7.3.1", "geoplanet:7.3.2", "geoplanet:7.4.0", "geoplanet:7.4.1", "geoplanet:7.5.1", "geoplanet:7.5.2", "geoplanet:7.6.0", "geoplanet:7.8.1", "geoplanet:7.9.0", "geoplanet:7.10.0", "geoplanet:8.0.0", "woeplanet:8.0.0"], "meta:indexed": "2020-08-20T20:47:37.616826", "meta:updated": "2020-08-22T02:46:11.992395", "woe:hierarchy": {"continent": 24865671, "country": 23424856, "town": 0, "planet": 1, "county": 0, "suburb": 0, "state": 2345891, "region": 0, "localadmin": 28423466}, "woe:timezone_id": 28350861, "woe:hash": "xn98c2brsyce", "woe:centroid": [137.164856, 36.69978], "geom:latitude": 36.69978, "geom:longitude": 137.164856, "geom:hash": "xn98c2brsyce", "woe:latitude": 36.69978, "geom:centroid": [137.164856, 36.69978], "woe:longitude": 137.164856, "woe:repo": "woeplanet-poi-jp"}, "geometry": {"coordinates": [137.164856, 36.69978], "type": "Point"}}