{"type": "Feature", "id": 28620067, "properties": {"woe:id": 28620067, "woe:parent_id": 28411141, "woe:name": "\u6728\u66f4\u6d25\u5bcc\u58eb\u5c4b\u5b63\u773a", "woe:placetype": 20, "woe:placetype_name": "POI", "woe:lang": "JPN", "iso:country": "JP", "meta:provider": ["geoplanet:7.3.1", "geoplanet:7.3.2", "geoplanet:7.4.0", "geoplanet:7.4.1", "geoplanet:7.5.1", "geoplanet:7.5.2", "geoplanet:7.6.0", "geoplanet:7.8.1", "geoplanet:7.9.0", "geoplanet:7.10.0", "geoplanet:8.0.0", "woeplanet:8.0.0"], "meta:indexed": "2020-08-20T20:47:36.397434", "woe:alias_JPN_V": ["\u5bcc\u58eb\u5c4b\u30db\u30c6\u30eb", "\u304d\u3055\u3089\u3065\u3075\u3058\u3084\u304d\u3061\u3087\u3046"], "meta:updated": "2020-08-22T02:46:11.250486", "woe:alias_ENG_P": ["Kisarazu Fujiya Kicho"], "woe:hierarchy": {"continent": 24865671, "country": 23424856, "town": 0, "planet": 1, "county": 0, "suburb": 0, "state": 2345854, "region": 0, "localadmin": 28411141}, "woe:timezone_id": 28350861, "woe:hash": "xn73rbu221vz", "woe:centroid": [139.916733, 35.38015], "geom:latitude": 35.38015, "geom:longitude": 139.916733, "geom:hash": "xn73rbu221vz", "woe:latitude": 35.38015, "geom:centroid": [139.916733, 35.38015], "woe:longitude": 139.916733, "woe:repo": "woeplanet-poi-jp"}, "geometry": {"coordinates": [139.916733, 35.38015], "type": "Point"}}