{"type": "Feature", "id": 28619194, "properties": {"woe:id": 28619194, "woe:parent_id": 1108063, "woe:name": "\u304d\u306c\u5ddd\u9928\u672c\u5e97", "woe:placetype": 20, "woe:placetype_name": "POI", "woe:lang": "JPN", "iso:country": "JP", "meta:provider": ["geoplanet:7.3.1", "geoplanet:7.3.2", "geoplanet:7.4.0", "geoplanet:7.4.1", "geoplanet:7.5.1", "geoplanet:7.5.2", "geoplanet:7.6.0", "geoplanet:7.8.1", "geoplanet:7.9.0", "geoplanet:7.10.0", "geoplanet:8.0.0", "woeplanet:8.0.0"], "meta:indexed": "2020-08-20T20:47:35.601954", "meta:updated": "2020-08-22T02:46:10.839694", "woe:hierarchy": {"continent": 24865671, "country": 23424856, "town": 0, "planet": 1, "county": 0, "suburb": 0, "state": 2345887, "region": 0, "localadmin": 1108063}, "woe:timezone_id": 28350861, "woe:hash": "xne3e3vgjveg", "woe:centroid": [139.721283, 36.83633], "geom:latitude": 36.83633, "geom:longitude": 139.721283, "geom:hash": "xne3e3vgjveg", "woe:latitude": 36.83633, "geom:centroid": [139.721283, 36.83633], "woe:longitude": 139.721283, "woe:repo": "woeplanet-poi-jp"}, "geometry": {"coordinates": [139.721283, 36.83633], "type": "Point"}}