{"type": "Feature", "id": 28621128, "properties": {"woe:id": 28621128, "woe:parent_id": 55807776, "woe:name": "\u8d8a\u5ddd\u65c5\u9928", "woe:placetype": 20, "woe:placetype_name": "POI", "woe:lang": "JPN", "iso:country": "JP", "meta:provider": ["geoplanet:7.3.1", "geoplanet:7.3.2", "geoplanet:7.4.0", "geoplanet:7.4.1", "geoplanet:7.5.1", "geoplanet:7.5.2", "geoplanet:7.6.0", "geoplanet:7.8.1", "geoplanet:7.9.0", "geoplanet:7.10.0", "geoplanet:8.0.0", "woeplanet:8.0.0"], "meta:indexed": "2020-08-20T20:47:37.217812", "meta:updated": "2020-08-22T02:46:11.771866", "woe:hierarchy": {"continent": 24865671, "country": 23424856, "town": 0, "planet": 1, "county": 55805803, "suburb": 0, "state": 2345878, "region": 0, "localadmin": 55807776}, "woe:timezone_id": 28350861, "woe:hash": "xndzsp5kjzgc", "woe:centroid": [139.047684, 37.92004], "geom:latitude": 37.92004, "geom:longitude": 139.047684, "geom:hash": "xndzsp5kjzgc", "woe:latitude": 37.92004, "geom:centroid": [139.047684, 37.92004], "woe:longitude": 139.047684, "woe:repo": "woeplanet-poi-jp"}, "geometry": {"coordinates": [139.047684, 37.92004], "type": "Point"}}