{"type": "Feature", "id": 28618102, "geometry": {"type": "Point", "coordinates": [140.656204, 39.50531]}, "properties": {"woe:id": 28618102, "woe:parent_id": 28395591, "woe:name": "\u592a\u7530\u56fd\u6c11\u4f11\u990a\u5730\u5965\u7fbd\u5c71\u8358", "woe:placetype": 20, "woe:placetype_name": "POI", "woe:lang": "JPN", "iso:country": "JP", "meta:provider": ["geoplanet:7.3.1", "geoplanet:7.3.2", "geoplanet:7.4.0", "geoplanet:7.4.1", "geoplanet:7.5.1", "geoplanet:7.5.2", "geoplanet:7.6.0", "geoplanet:7.8.1", "geoplanet:7.9.0", "geoplanet:7.10.0", "geoplanet:8.0.0", "woeplanet:8.0.0"], "meta:indexed": "2020-08-20T20:47:34.713452", "woe:alias_JPN_V": ["\u304a\u304a\u305f\u3053\u304f\u307f\u3093\u304d\u3085\u3046\u3088\u3046\u3061\u304a\u3046\u3046\u3055\u3093\u305d\u3046"], "meta:updated": "2020-10-14T12:09:54.988354", "woe:alias_ENG_P": ["Oota Kokumin Kyuyochi Ouusanso"], "woe:hierarchy": {"continent": 24865671, "country": 23424856, "town": 0, "planet": 1, "county": 0, "suburb": 0, "state": 2345852, "region": 0, "localadmin": 28395591}, "woe:timezone_id": 28350861, "woe:hash": "xph08xwxp5e3", "woe:centroid": [140.656204, 39.50531], "geom:latitude": 39.50531, "geom:longitude": 140.656204, "geom:hash": "xph08xwxp5e3", "woe:latitude": 39.50531, "geom:centroid": [140.656204, 39.50531], "woe:longitude": 140.656204, "woe:repo": "woeplanet-poi-jp", "geom:area": 0.0, "woe:scale": 19}}