{"type": "Feature", "id": 28619287, "properties": {"woe:id": 28619287, "woe:parent_id": 28405145, "woe:name": "\u5ddd\u4fe3\u6e29\u6cc9\u30db\u30c6\u30eb\u3075\u304f\u3088\u9928", "woe:placetype": 20, "woe:placetype_name": "POI", "woe:lang": "JPN", "iso:country": "JP", "meta:provider": ["geoplanet:7.3.1", "geoplanet:7.3.2", "geoplanet:7.4.0", "geoplanet:7.4.1", "geoplanet:7.5.1", "geoplanet:7.5.2", "geoplanet:7.6.0", "geoplanet:7.8.1", "geoplanet:7.9.0", "geoplanet:7.10.0", "geoplanet:8.0.0", "woeplanet:8.0.0"], "meta:indexed": "2020-08-20T20:47:35.677418", "woe:alias_JPN_V": ["\u304b\u308f\u307e\u305f\u304a\u3093\u305b\u3093\u307b\u3066\u308b\u3075\u304f\u3088\u304b\u3093"], "meta:updated": "2020-08-22T02:46:10.884782", "woe:alias_ENG_P": ["Kawamata Onsen Hotel Hukuyokan"], "woe:hierarchy": {"continent": 24865671, "country": 23424856, "town": 0, "planet": 1, "county": 0, "suburb": 0, "state": 2345887, "region": 0, "localadmin": 28405145}, "woe:timezone_id": 28350861, "woe:hash": "xne1v9cxz5g3", "woe:centroid": [139.462814, 36.881081], "geom:latitude": 36.881081, "geom:longitude": 139.462814, "geom:hash": "xne1v9cxz5g3", "woe:latitude": 36.881081, "geom:centroid": [139.462814, 36.881081], "woe:longitude": 139.462814, "woe:repo": "woeplanet-poi-jp"}, "geometry": {"coordinates": [139.462814, 36.881081], "type": "Point"}}