{"type": "Feature", "id": 28619248, "properties": {"woe:id": 28619248, "woe:parent_id": 28405149, "woe:name": "\u9b3c\u6012\u5ddd\u30b0\u30ea\u30fc\u30f3\u30d1\u30ec\u30b9", "woe:placetype": 20, "woe:placetype_name": "POI", "woe:lang": "JPN", "iso:country": "JP", "meta:provider": ["geoplanet:7.3.1", "geoplanet:7.3.2", "geoplanet:7.4.0", "geoplanet:7.4.1", "geoplanet:7.5.1", "geoplanet:7.5.2", "geoplanet:7.6.0", "geoplanet:7.8.1", "geoplanet:7.9.0", "geoplanet:7.10.0", "geoplanet:8.0.0", "woeplanet:8.0.0"], "meta:indexed": "2020-08-20T20:47:35.646728", "woe:alias_JPN_V": ["\u304d\u306c\u304c\u308f\u3050\u308a\u30fc\u3093\u3071\u308c\u3059"], "meta:updated": "2020-08-22T02:46:10.865598", "woe:alias_ENG_P": ["Kinugawa Green Palace"], "woe:hierarchy": {"continent": 24865671, "country": 23424856, "town": 0, "planet": 1, "county": 0, "suburb": 0, "state": 2345887, "region": 0, "localadmin": 28405149}, "woe:timezone_id": 28350861, "woe:hash": "xne3e6t2q9ft", "woe:centroid": [139.720627, 36.839958], "geom:latitude": 36.839958, "geom:longitude": 139.720627, "geom:hash": "xne3e6t2q9ft", "woe:latitude": 36.839958, "geom:centroid": [139.720627, 36.839958], "woe:longitude": 139.720627, "woe:repo": "woeplanet-poi-jp"}, "geometry": {"coordinates": [139.720627, 36.839958], "type": "Point"}}