{"type": "Feature", "id": 28617521, "properties": {"woe:id": 28617521, "woe:parent_id": 28389468, "woe:name": "\u56db\u5b63\u4ead", "woe:placetype": 20, "woe:placetype_name": "POI", "woe:lang": "JPN", "iso:country": "JP", "meta:provider": ["geoplanet:7.3.1", "geoplanet:7.3.2", "geoplanet:7.4.0", "geoplanet:7.4.1", "geoplanet:7.5.1", "geoplanet:7.5.2", "geoplanet:7.6.0", "geoplanet:7.8.1", "geoplanet:7.9.0", "geoplanet:7.10.0", "geoplanet:8.0.0", "woeplanet:8.0.0"], "meta:indexed": "2020-08-20T20:47:34.270227", "woe:alias_JPN_V": ["\u3057\u304d\u3066\u3044"], "meta:updated": "2020-08-22T02:46:10.226752", "woe:alias_ENG_P": ["Shikitei"], "woe:hierarchy": {"continent": 24865671, "country": 23424856, "town": 0, "planet": 1, "county": 0, "suburb": 0, "state": 2345865, "region": 0, "localadmin": 28389468}, "woe:timezone_id": 28350861, "woe:hash": "xph39n62q8d3", "woe:centroid": [141.02388, 39.67305], "geom:latitude": 39.67305, "geom:longitude": 141.02388, "geom:hash": "xph39n62q8d3", "woe:latitude": 39.67305, "geom:centroid": [141.02388, 39.67305], "woe:longitude": 141.02388, "woe:repo": "woeplanet-poi-jp"}, "geometry": {"coordinates": [141.02388, 39.67305], "type": "Point"}}