{"type": "Feature", "id": 28619307, "properties": {"woe:id": 28619307, "woe:parent_id": 28405111, "woe:name": "\u307b\u306e\u304b\u306a\u5bbf\u6a39\u6797", "woe:placetype": 20, "woe:placetype_name": "POI", "woe:lang": "JPN", "iso:country": "JP", "meta:provider": ["geoplanet:7.3.1", "geoplanet:7.3.2", "geoplanet:7.4.0", "geoplanet:7.4.1", "geoplanet:7.5.1", "geoplanet:7.5.2", "geoplanet:7.6.0", "geoplanet:7.8.1", "geoplanet:7.9.0", "geoplanet:7.10.0", "geoplanet:8.0.0", "woeplanet:8.0.0"], "meta:indexed": "2020-08-20T20:47:35.691359", "woe:alias_JPN_V": ["\u65e5\u5149\u30b0\u30e9\u30f3\u30c9\u30db\u30c6\u30eb", "\u307b\u306e\u304b\u306a\u3084\u3069\u3058\u3085\u308a\u3093"], "meta:updated": "2020-08-22T02:46:10.894164", "woe:alias_ENG_P": ["Honokanayado Jurin"], "woe:hierarchy": {"continent": 24865671, "country": 23424856, "town": 0, "planet": 1, "county": 0, "suburb": 0, "state": 2345887, "region": 0, "localadmin": 28405111}, "woe:timezone_id": 28350861, "woe:hash": "xne1ks44gpnw", "woe:centroid": [139.419388, 36.80471], "geom:latitude": 36.80471, "geom:longitude": 139.419388, "geom:hash": "xne1ks44gpnw", "woe:latitude": 36.80471, "geom:centroid": [139.419388, 36.80471], "woe:longitude": 139.419388, "woe:repo": "woeplanet-poi-jp"}, "geometry": {"coordinates": [139.419388, 36.80471], "type": "Point"}}