{"type": "Feature", "id": 28616567, "properties": {"woe:id": 28616567, "woe:parent_id": 28379882, "woe:name": "\u306c\u304f\u3082\u308a\u306e\u5bbf\u3075\u308b\u5ddd", "woe:placetype": 20, "woe:placetype_name": "POI", "woe:lang": "JPN", "iso:country": "JP", "meta:provider": ["geoplanet:7.3.1", "geoplanet:7.3.2", "geoplanet:7.4.0", "geoplanet:7.4.1", "geoplanet:7.5.1", "geoplanet:7.5.2", "geoplanet:7.6.0", "geoplanet:7.8.1", "geoplanet:7.9.0", "geoplanet:7.10.0", "geoplanet:8.0.0", "woeplanet:8.0.0"], "meta:indexed": "2020-08-20T20:47:33.426708", "woe:alias_JPN_V": ["\u306c\u304f\u3082\u308a\u306e\u3084\u3069\u3075\u308b\u304b\u308f"], "meta:updated": "2020-08-22T02:46:09.892266", "woe:alias_ENG_P": ["Nukumorinoyado Furukawa"], "woe:hierarchy": {"continent": 24865671, "country": 23424856, "town": 0, "planet": 1, "county": 1111800, "suburb": 0, "state": 7153351, "region": 0, "localadmin": 28379882}, "woe:timezone_id": 28350861, "woe:hash": "xpskkjwkumyw", "woe:centroid": [141.161118, 42.96563], "geom:latitude": 42.96563, "geom:longitude": 141.161118, "geom:hash": "xpskkjwkumyw", "woe:latitude": 42.96563, "geom:centroid": [141.161118, 42.96563], "woe:longitude": 141.161118, "woe:repo": "woeplanet-poi-jp"}, "geometry": {"coordinates": [141.161118, 42.96563], "type": "Point"}}